{
  "filename": "4091c950-60ce-4a56-9ea7-e33004abc555.pdf",
  "timestamp": "2025-10-13T09:50:46.246Z",
  "processingTime": 5736,
  "confidence": 92,
  "rawText": "\n\n\"Best Student\" Award – Received 4 times during college tenure\nOrange World Record Holder – Completed 1144.10 hours non-stop online Mutamil Kalai Villa (May–July\n2021)\nZonal Level Finalist – Federal Bank Speak for India Competition\nDistrict Level First Prize – Poetry competition (Awarded by Collector Mr. Meganatha Reddy, IAS)\nAwardee – Speech competition, Book Festival (Awarded by Collector Mr. V.P. Jeyaselan, IAS)\nA  passionate  and  dynamic  teaching  professional  specializing  in  Commerce  and  Accountancy,  aiming  to\nfoster  a  love  for  learning  through  motivational  and  interactive  teaching  methods.  With  a  strong  academic\nbackground,  extensive  public  speaking  experience,  and  a  proven  record  of  leadership,  I  seek  to  contribute\neffectively to the holistic development of students while continually evolving as an educator.\nQualification                                                           Institution                                                  Year of Completion\nB.Ed                                                             P.S.N.L College, Sattur                                                    2025\nM.Com                                                   Sri Krishnasamy College, Sattur                                           2023\nB.Com                                                   Sri Krishnasamy College, Sattur                                            2021\nIntern Teacher\nSubject Expertise: Commerce, Accountancy\nPublic Speaking & Communication\nLeadership & Motivation\nCreative Writing & Poetry\nClassroom Management\nEvent Coordination\nStudent Engagement Strategies\nMotivational speaker with over 204 stage\nappearances.\nGuest Speaker at JCI and Rotary Club events\nin Sattur and Sivakasi.\nCo-author of 6 published books (Poetry and\nLiterature).\nEvent Organizer – Successfully organized and\nmanaged various programs and cultural events\nin college\nMunicipal Higher Secondary School, Sattur\nTaught PG school students for 80 days as part of B.Ed internship\nDeveloped lesson plans, assessed student progress, and conducted engaging classroom sessions\nSep - Jan\nP R O F E S S I O N A L   O B J E C T I V E\nP U B L I C   S P E A K E R\n6381564418    |    tkarthi6381@gmail.com\nKARTHIK KUMAR T\nT E A C H I N G   E X P E R I E N C E\nA W A R D S  &  A C H I E V E M E N T S\nK E Y   S K I L L SL E A D E R S H I P  &  E V E N T   M A N A G E M E N T\nE D U C A T I O N A L   Q U A L I F I C A T I O N S",
  "extractedData": {
    "name": "Karthik Kumar T",
    "email": "tkarthi6381@gmail.com",
    "phone": "6381564418",
    "linkedinUrl": null,
    "githubUrl": null,
    "portfolioUrl": null,
    "location": null,
    "title": "Teaching Professional",
    "summary": "A passionate and dynamic teaching professional specializing in Commerce and Accountancy, aiming to foster a love for learning through motivational and interactive teaching methods. With a strong academic background, extensive public speaking experience, and a proven record of leadership, I seek to contribute effectively to the holistic development of students while continually evolving as an educator.",
    "experience": [
      {
        "jobTitle": "Intern Teacher",
        "company": "Municipal Higher Secondary School, Sattur",
        "duration": "Sep - Jan",
        "startDate": null,
        "endDate": null,
        "techUsed": [],
        "description": "Taught PG school students for 80 days as part of B.Ed internship. Developed lesson plans, assessed student progress, and conducted engaging classroom sessions.",
        "achievements": []
      }
    ],
    "education": [
      {
        "degree": "B.Ed",
        "field": null,
        "university": "P.S.N.L College, Sattur",
        "year": "2025",
        "percentage": null,
        "gpa": null,
        "location": "Sattur"
      },
      {
        "degree": "M.Com",
        "field": null,
        "university": "Sri Krishnasamy College, Sattur",
        "year": "2023",
        "percentage": null,
        "gpa": null,
        "location": "Sattur"
      },
      {
        "degree": "B.Com",
        "field": null,
        "university": "Sri Krishnasamy College, Sattur",
        "year": "2021",
        "percentage": null,
        "gpa": null,
        "location": "Sattur"
      }
    ],
    "projects": [],
    "achievements": [
      {
        "title": "\"Best Student\" Award",
        "description": "Received 4 times during college tenure",
        "year": null,
        "organization": null
      },
      {
        "title": "Orange World Record Holder",
        "description": "Completed 1144.10 hours non-stop online Mutamil Kalai Villa",
        "year": "May–July 2021",
        "organization": null
      },
      {
        "title": "Zonal Level Finalist",
        "description": "Federal Bank Speak for India Competition",
        "year": null,
        "organization": null
      },
      {
        "title": "District Level First Prize",
        "description": "Poetry competition (Awarded by Collector Mr. Meganatha Reddy, IAS)",
        "year": null,
        "organization": null
      },
      {
        "title": "Awardee",
        "description": "Speech competition, Book Festival (Awarded by Collector Mr. V.P. Jeyaselan, IAS)",
        "year": null,
        "organization": null
      }
    ],
    "certifications": [],
    "skills": [
      "Commerce",
      "Accountancy",
      "Public Speaking & Communication",
      "Leadership & Motivation",
      "Creative Writing & Poetry",
      "Classroom Management",
      "Event Coordination",
      "Student Engagement Strategies"
    ],
    "interests": [],
    "languages": [],
    "salary": null,
    "availability": null,
    "remotePreference": null,
    "visaStatus": null,
    "originalData": {
      "filename": "4091c950-60ce-4a56-9ea7-e33004abc555.pdf",
      "rawText": "\"Best Student\" Award – Received 4 times during college tenure Orange World Record Holder – Completed 1144.10 hours non-stop online Mutamil Kalai Villa (May–July 2021) Zonal Level Finalist – Federal Bank Speak for India Competition District Level First Prize – Poetry competition (Awarded by Collector Mr. Meganatha Reddy, IAS) Awardee – Speech competition, Book Festival (Awarded by Collector Mr. V.P. Jeyaselan, IAS) A passionate and dynamic teaching professional specializing in Commerce and Accountancy, aiming to foster a love for learning through motivational and interactive teaching methods. With a strong academic background, extensive public speaking experience, and a proven record of leadership, I seek to contribute effectively to the holistic development of students while continually evolving as an educator. Qualification Institution Year of Completion B.Ed P.S.N.L College, Sattur 2025 M.Com Sri Krishnasamy College, Sattur 2023 B.Com Sri Krishnasamy College, Sattur 2021 Intern Teacher Subject Expertise: Commerce, Accountancy Public Speaking & Communication Leadership & Motivation Creative Writing & Poetry Classroom Management Event Coordination Student Engagement Strategies Motivational speaker with over 204 stage appearances. Guest Speaker at JCI and Rotary Club events in Sattur and Sivakasi. Co-author of 6 published books (Poetry and Literature). Event Organizer – Successfully organized and managed various programs and cultural events in college Municipal Higher Secondary School, Sattur Taught PG school students for 80 days as part of B.Ed internship Developed lesson plans, assessed student progress, and conducted engaging classroom sessions Sep - Jan P R O F E S S I O N A L O B J E C T I V E P U B L I C S P E A K E R 6381564418 | tkarthi6381@gmail.com KARTHIK KUMAR T T E A C H I N G E X P E R I E N C E A W A R D S & A C H I E V E M E N T S K E Y S K I L L SL E A D E R S H I P & E V E N T M A N A G E M E N T E D U C A T I O N A L Q U A L I F I C A T I O N S"
    },
    "source": "resume",
    "confidence": 92,
    "processingTime": 0
  }
}