{
  "filename": "62951453-8125-436f-9fda-b68e81f0653b.pdf",
  "timestamp": "2025-10-13T11:55:23.402Z",
  "processingTime": 5182,
  "confidence": 93,
  "rawText": "\n\nSoumyadeep Sen\n7488079311|soumyadeepbksc@gmail.com||\nProfile Summary\nSoftware Engineer with Total 4+ years of IT experience in full stack development and application support,\ncomplemented by a Google Cloud Certified Associate Cloud Engineer credential.Experienced in handling client\nissues, alerts, ServiceNow tickets, and reporting while collaborating in enterprise environments.  Strong interest\nin transitioning into Cloud Administration  Monitoring (LogicMonitor, GCP) roles, leveraging certification and\npractical exposure to GCP services, Cloud Console, and Storage.\nExperience\nTata Consultancy Services|System Engineer08/2021-Present\n•\nSupported client projects with a mix of development, monitoring, and issue resolution activities.\n•\nExposure to Google Cloud Platform (GCP) through certification and practical usage in managing Cloud Console\nStorage.\n•\nResolved client enrollment and login issues using Java and PostgreSQL for the Cetera Financial Group client.\n•\nHandled ServiceNow tickets and performed proactive monitoring of alerts, escalating and resolving issues as per\nSLA.\n•\nDeveloped Web APIs (ASP.Net, Node.js) and contributed to application enhancements.\n•\nCollaborated in full stack development (HTML, CSS, JavaScript, Angular, React.js, Java, MySQL) for Citi Bank\nproject.\n•\nCollaborated in reporting, debugging, and proactive monitoring for client applications, ensuring smooth operations.\nTechnical Skills\nCloud  Monitoring:  Google Cloud Platform (GCP), Cloud Console, Cloud Storage, Proactive Monitoring  Alerts,\nServiceNow Ticketing\nProgramming  Frameworks:  Java, Node.js, React.js, ASP.Net, Web API\nOther Tools:  MS Excel, MYSQL\nCourses and Certifications\nGoogle Cloud Certified Associate Cloud Engineer|Valid Till May 2026\nEducation\nInstitute Of Engineering and Management, KolkataKolkata, West Bengal\nBachelor Of Technology, in Electrical And Electronics EngineeringAug. 2017 – July 2021\nHoly Cross SchoolBokaro Steel City, Jharkhand\nHigh SchoolJuly. 2014 – June 2016\nExtracurricular Activities\nMember of Institute Football Team|\n•\nRepresented the institute in intercollegiate football tournaments.",
  "extractedData": {
    "name": "Soumyadeep Sen",
    "email": "soumyadeepbksc@gmail.com",
    "phone": "7488079311",
    "linkedinUrl": null,
    "githubUrl": null,
    "portfolioUrl": null,
    "location": null,
    "title": "Software Engineer",
    "summary": "Software Engineer with Total 4+ years of IT experience in full stack development and application support, complemented by a Google Cloud Certified Associate Cloud Engineer credential. Experienced in handling client issues, alerts, ServiceNow tickets, and reporting while collaborating in enterprise environments. Strong interest in transitioning into Cloud Administration Monitoring (LogicMonitor, GCP) roles, leveraging certification and practical exposure to GCP services, Cloud Console, and Storage.",
    "experience": [
      {
        "jobTitle": "System Engineer",
        "company": "Tata Consultancy Services",
        "duration": "08/2021-Present",
        "startDate": "2021-08",
        "endDate": "Present",
        "techUsed": [
          "Google Cloud Platform",
          "Java",
          "PostgreSQL",
          "ASP.Net",
          "Node.js",
          "HTML",
          "CSS",
          "JavaScript",
          "Angular",
          "React.js",
          "MySQL"
        ],
        "description": "Supported client projects with a mix of development, monitoring, and issue resolution activities. Exposure to Google Cloud Platform (GCP) through certification and practical usage in managing Cloud Console Storage. Resolved client enrollment and login issues using Java and PostgreSQL for the Cetera Financial Group client. Handled ServiceNow tickets and performed proactive monitoring of alerts, escalating and resolving issues as per SLA. Developed Web APIs (ASP.Net, Node.js) and contributed to application enhancements. Collaborated in full stack development (HTML, CSS, JavaScript, Angular, React.js, Java, MySQL) for Citi Bank project. Collaborated in reporting, debugging, and proactive monitoring for client applications, ensuring smooth operations.",
        "achievements": []
      }
    ],
    "education": [
      {
        "degree": "Bachelor Of Technology",
        "field": "Electrical And Electronics Engineering",
        "university": "Institute Of Engineering and Management, Kolkata",
        "year": "2021",
        "percentage": null,
        "gpa": null,
        "location": "Kolkata, West Bengal"
      },
      {
        "degree": "High School",
        "field": null,
        "university": "Holy Cross School",
        "year": "2016",
        "percentage": null,
        "gpa": null,
        "location": "Bokaro Steel City, Jharkhand"
      }
    ],
    "projects": [],
    "achievements": [],
    "certifications": [
      {
        "name": "Google Cloud Certified Associate Cloud Engineer",
        "issuer": null,
        "date": null,
        "expiryDate": "2026-05",
        "credentialId": null,
        "url": null
      }
    ],
    "skills": [
      "Google Cloud Platform",
      "Cloud Console",
      "Cloud Storage",
      "Proactive Monitoring Alerts",
      "ServiceNow Ticketing",
      "Java",
      "Node.js",
      "React.js",
      "ASP.Net",
      "Web API",
      "MS Excel",
      "MYSQL"
    ],
    "interests": [],
    "languages": [],
    "salary": null,
    "availability": null,
    "remotePreference": null,
    "visaStatus": null,
    "originalData": {
      "filename": "62951453-8125-436f-9fda-b68e81f0653b.pdf",
      "rawText": "Soumyadeep Sen 7488079311|soumyadeepbksc@gmail.com|| Profile Summary Software Engineer with Total 4+ years of IT experience in full stack development and application support, complemented by a Google Cloud Certified Associate Cloud Engineer credential.Experienced in handling client issues, alerts, ServiceNow tickets, and reporting while collaborating in enterprise environments. Strong interest in transitioning into Cloud Administration Monitoring (LogicMonitor, GCP) roles, leveraging certification and practical exposure to GCP services, Cloud Console, and Storage. Experience Tata Consultancy Services|System Engineer08/2021-Present • Supported client projects with a mix of development, monitoring, and issue resolution activities. • Exposure to Google Cloud Platform (GCP) through certification and practical usage in managing Cloud Console Storage. • Resolved client enrollment and login issues using Java and PostgreSQL for the Cetera Financial Group client. • Handled ServiceNow tickets and performed proactive monitoring of alerts, escalating and resolving issues as per SLA. • Developed Web APIs (ASP.Net, Node.js) and contributed to application enhancements. • Collaborated in full stack development (HTML, CSS, JavaScript, Angular, React.js, Java, MySQL) for Citi Bank project. • Collaborated in reporting, debugging, and proactive monitoring for client applications, ensuring smooth operations. Technical Skills Cloud Monitoring: Google Cloud Platform (GCP), Cloud Console, Cloud Storage, Proactive Monitoring Alerts, ServiceNow Ticketing Programming Frameworks: Java, Node.js, React.js, ASP.Net, Web API Other Tools: MS Excel, MYSQL Courses and Certifications Google Cloud Certified Associate Cloud Engineer|Valid Till May 2026 Education Institute Of Engineering and Management, KolkataKolkata, West Bengal Bachelor Of Technology, in Electrical And Electronics EngineeringAug. 2017 – July 2021 Holy Cross SchoolBokaro Steel City, Jharkhand High SchoolJuly. 2014 – June 2016 Extracurr"
    },
    "source": "resume",
    "confidence": 93,
    "processingTime": 0
  }
}