{
  "filename": "8203e3bb-0c0c-4c9f-b1a0-b2741d08c491.pdf",
  "timestamp": "2025-10-13T11:55:39.111Z",
  "processingTime": 11083,
  "confidence": 95,
  "rawText": "\n\nSACHIN TUPSAMUNDAR\nAI Engineer\nsachin.tupsamundar.ai@gmail.com\n \n+91 9822022834\n \nParbhani, India\n \nGithub\n \nLinkedin\n \nPortfolio\n \nPROFILE\nAI  Product  Engineer  with 2+  years  of  expeience  and  proven  track  record  of transforming  cutting-edge  Generative  AI  research  into\ncommercially viable products. I design and deploy Agentic AI systems, multi-modal LLM applications, and enterprise-scale RAG pipelines\nthat deliver measurable business outcomes — including 30% operational cost savings and 25%+ user engagement growth.\nMy expertise spans the full AI lifecycle: model architecture, LangGraph/LangChain orchestration, LLMOps pipelines, and scalable \ndeployments on AWS, GCP, and Azure. With a strong foundation in mathematics and hands-on experience in LLM fine-tuning (LoRA/QLoRA) \nand vector database integration (Pinecone, ChromaDB), I build robust, production-ready AI solutions that deliver lasting impact.\nPROFESSIONAL EXPERIENCE\nArtificial Intelligence Engineer                                                                                                                                                                               Dolf Technologies Pvt. Ltd\n04/2025 - Present\n•Architected and deployed a conversational Agentic AI system that automated initial resume screening and applicant query handling, \nreducing recruiter workload by 30%.\n•Designed and implemented an enterprise-grade RAG pipeline with LangChain + Pinecone, improving recruiter satisfaction scores by 20% \nthrough precise, context-aware candidate insights.\n•Fine-tuned Google Gemini LLM using LoRA for domain-specific talent analysis, enhancing accuracy of candidate qualification matching by \n22%.\n•Deployed the agent as a scalable microservice on AWS using Docker and CI/CD pipelines, ensuring 99.9% uptime and seamless integration \ninto HR platforms.\n•Established a feedback-driven active learning loop that improved model precision from 84% to 96% in three months based on recruiter-\napproved training data.\n•Developed an interactive recruiter dashboard in Streamlit for managing AI agents, reviewing candidate summaries, and tracking hiring KPIs \nin real time.\n•Collaborated with the HR analytics team to integrate agent insights into company-wide recruitment dashboards, enabling leadership to \ntrack hiring efficiency and candidate quality trends in real time.\n•Tech Stack: Agentic AI, Google Gemini, LoRA, LangChain, LangGraph, Pinecone, RAG, Docker, AWS, Streamlit, Git/GitHub.\nJr. Artificial Intelligence Engineer                                                                                                                                                                       Dolf Technologies Pvt. Ltd\n08/2023 - 03/2025\n•Engineered a multi-modal Generative AI fitness coach that generated dynamic workout and nutrition plans tailored to individual user goals.\n•Integrated a custom LLM for exercise suggestions, diet planning, progress tracking, and calorie estimation, achieving 92% accuracy in form \ndetection via a YOLO-based CV pipeline.\n•Built a real-time visual feedback system that processed user-uploaded images to provide adaptive coaching, increasing workout completion \nrates by 25%.\n•Leveraged LangGraph to orchestrate adaptive multi-agent workflows that evolved recommendations based on live user feedback and \nactivity tracking.\n•Designed and deployed a Streamlit UI for an engaging and motivational user experience, incorporating advanced prompt engineering for \npersonalized conversation flows.\n•Led end-to-end project lifecycle management, collaborating with designers, backend engineers, and product managers, and conducting \nweekly Jira-based sprint reviews and code walkthroughs.\n•Implemented MLOps best practices with MLflow tracking and GCP Vertex AI pipelines, reducing model retraining time by 40% and ensuring \nreproducibility of experiments.\n•Tech Stack: Multi-modal AI, YOLO, LLMs, LangGraph, Computer Vision, Prompt Engineering, Streamlit, MLOps, MLflow, GCP, Git/GitHub.\nSKILLS\n•AI Systems: Agentic AI, RAG, LangGraph, LangChain, Autogen, MCP, n8n, Agno, CrewAI\n•LLMs: Google Gemini, OpenAI GPT, LLaMA, Mistral, Groq\n•Multi-modal AI: YOLO, image-text pipelines, visual feedback systems\n•ML/DL: LSTM RNN, Transformers (BERT, GPT), RLHF, PEFT, LoRA/QLoRA fine-tuning.\n•Neural Networks: ANN, RNN, CNN\n•MLOps/LLMOps: MLflow, Docker, Kubernetes, AWS SageMaker, GCP Vertex AI, Azure ML\n•Vector Databases: Pinecone, ChromaDB\n•Programming & Data Tools: Python, SQL, Pandas, NumPy, Matplotlib, Scikit-learn, TensorFlow, PyTorch, Keras\n•Cloud Platforms: AWS, GCP, Azure\n•Tools: HuggingFace, Streamlit, FastAPI, Jira, Git/GitHub\n•Methodologies: Agile, CI/CD, Prompt Engineering, Retrieval-Augmented Generation (RAG), Multi-modal AI\nEDUCATION\nD. Y. Patil College of Engineering Akurdi, Pune\nCGPA - 8.4\n2019 – 2023\nCERTIFICATE\n•Complete Generative AI With Langchain and Huggingface\n•Complete Agentic AI With LangGraph and Langchain\n•Building AI Agents And Agentic AI System With Microsoft Autogen",
  "extractedData": {
    "name": "SACHIN TUPSAMUNDAR",
    "email": "sachin.tupsamundar.ai@gmail.com",
    "phone": "+91 9822022834",
    "linkedinUrl": "https://www.linkedin.com/in/sachin-tupsamundar-ai",
    "githubUrl": "https://github.com/Mr-aicoder",
    "portfolioUrl": "https://mr-aicoder.github.io/Portfolio_Web_2/",
    "location": "Parbhani, India",
    "title": "AI Engineer",
    "summary": "AI Product Engineer with 2+ years of experience and proven track record of transforming cutting-edge Generative AI research into commercially viable products. I design and deploy Agentic AI systems, multi-modal LLM applications, and enterprise-scale RAG pipelines that deliver measurable business outcomes — including 30% operational cost savings and 25%+ user engagement growth. My expertise spans the full AI lifecycle: model architecture, LangGraph/LangChain orchestration, LLMOps pipelines, and scalable deployments on AWS, GCP, and Azure. With a strong foundation in mathematics and hands-on experience in LLM fine-tuning (LoRA/QLoRA) and vector database integration (Pinecone, ChromaDB), I build robust, production-ready AI solutions that deliver lasting impact.",
    "experience": [
      {
        "jobTitle": "Artificial Intelligence Engineer",
        "company": "Dolf Technologies Pvt. Ltd",
        "duration": "04/2025 - Present",
        "startDate": "2025-04",
        "endDate": "Present",
        "techUsed": [
          "Agentic AI",
          "Google Gemini",
          "LoRA",
          "LangChain",
          "LangGraph",
          "Pinecone",
          "RAG",
          "Docker",
          "AWS",
          "Streamlit",
          "Git/GitHub"
        ],
        "description": "Architected and deployed a conversational Agentic AI system that automated initial resume screening and applicant query handling, reducing recruiter workload by 30%. Designed and implemented an enterprise-grade RAG pipeline with LangChain + Pinecone, improving recruiter satisfaction scores by 20% through precise, context-aware candidate insights. Fine-tuned Google Gemini LLM using LoRA for domain-specific talent analysis, enhancing accuracy of candidate qualification matching by 22%. Deployed the agent as a scalable microservice on AWS using Docker and CI/CD pipelines, ensuring 99.9% uptime and seamless integration into HR platforms. Established a feedback-driven active learning loop that improved model precision from 84% to 96% in three months based on recruiter-approved training data. Developed an interactive recruiter dashboard in Streamlit for managing AI agents, reviewing candidate summaries, and tracking hiring KPIs in real time. Collaborated with the HR analytics team to integrate agent insights into company-wide recruitment dashboards, enabling leadership to track hiring efficiency and candidate quality trends in real time.",
        "achievements": []
      },
      {
        "jobTitle": "Jr. Artificial Intelligence Engineer",
        "company": "Dolf Technologies Pvt. Ltd",
        "duration": "08/2023 - 03/2025",
        "startDate": "2023-08",
        "endDate": "2025-03",
        "techUsed": [
          "Multi-modal AI",
          "YOLO",
          "LLMs",
          "LangGraph",
          "Computer Vision",
          "Prompt Engineering",
          "Streamlit",
          "MLOps",
          "MLflow",
          "GCP",
          "Git/GitHub"
        ],
        "description": "Engineered a multi-modal Generative AI fitness coach that generated dynamic workout and nutrition plans tailored to individual user goals. Integrated a custom LLM for exercise suggestions, diet planning, progress tracking, and calorie estimation, achieving 92% accuracy in form detection via a YOLO-based CV pipeline. Built a real-time visual feedback system that processed user-uploaded images to provide adaptive coaching, increasing workout completion rates by 25%. Leveraged LangGraph to orchestrate adaptive multi-agent workflows that evolved recommendations based on live user feedback and activity tracking. Designed and deployed a Streamlit UI for an engaging and motivational user experience, incorporating advanced prompt engineering for personalized conversation flows. Led end-to-end project lifecycle management, collaborating with designers, backend engineers, and product managers, and conducting weekly Jira-based sprint reviews and code walkthroughs. Implemented MLOps best practices with MLflow tracking and GCP Vertex AI pipelines, reducing model retraining time by 40% and ensuring reproducibility of experiments.",
        "achievements": []
      }
    ],
    "education": [
      {
        "degree": null,
        "field": null,
        "university": "D. Y. Patil College of Engineering",
        "year": "2023",
        "percentage": null,
        "gpa": "8.4",
        "location": "Akurdi, Pune"
      }
    ],
    "projects": [],
    "achievements": [],
    "certifications": [
      {
        "name": "Complete Generative AI With Langchain and Huggingface",
        "issuer": null,
        "date": null,
        "expiryDate": null,
        "credentialId": null,
        "url": null
      },
      {
        "name": "Complete Agentic AI With LangGraph and Langchain",
        "issuer": null,
        "date": null,
        "expiryDate": null,
        "credentialId": null,
        "url": null
      },
      {
        "name": "Building AI Agents And Agentic AI System With Microsoft Autogen",
        "issuer": null,
        "date": null,
        "expiryDate": null,
        "credentialId": null,
        "url": null
      }
    ],
    "skills": [
      "Agentic AI",
      "RAG",
      "LangGraph",
      "LangChain",
      "Autogen",
      "MCP",
      "n8n",
      "Agno",
      "CrewAI",
      "Google Gemini",
      "OpenAI GPT",
      "LLaMA",
      "Mistral",
      "Groq",
      "YOLO",
      "image-text pipelines",
      "visual feedback systems",
      "LSTM RNN",
      "Transformers (BERT, GPT)",
      "RLHF",
      "PEFT",
      "LoRA/QLoRA fine-tuning",
      "ANN",
      "RNN",
      "CNN",
      "MLflow",
      "Docker",
      "Kubernetes",
      "AWS SageMaker",
      "GCP Vertex AI",
      "Azure ML",
      "Pinecone",
      "ChromaDB",
      "Python",
      "SQL",
      "Pandas",
      "NumPy",
      "Matplotlib",
      "Scikit-learn",
      "TensorFlow",
      "PyTorch",
      "Keras",
      "AWS",
      "GCP",
      "Azure",
      "HuggingFace",
      "Streamlit",
      "FastAPI",
      "Jira",
      "Git/GitHub",
      "Agile",
      "CI/CD",
      "Prompt Engineering",
      "Retrieval-Augmented Generation (RAG)",
      "Multi-modal AI"
    ],
    "interests": [],
    "languages": [],
    "salary": null,
    "availability": null,
    "remotePreference": null,
    "visaStatus": null,
    "originalData": {
      "filename": "8203e3bb-0c0c-4c9f-b1a0-b2741d08c491.pdf",
      "rawText": "SACHIN TUPSAMUNDAR AI Engineer sachin.tupsamundar.ai@gmail.com +91 9822022834 Parbhani, India Github Linkedin Portfolio PROFILE AI Product Engineer with 2+ years of expeience and proven track record of transforming cutting-edge Generative AI research into commercially viable products. I design and deploy Agentic AI systems, multi-modal LLM applications, and enterprise-scale RAG pipelines that deliver measurable business outcomes — including 30% operational cost savings and 25%+ user engagement growth. My expertise spans the full AI lifecycle: model architecture, LangGraph/LangChain orchestration, LLMOps pipelines, and scalable deployments on AWS, GCP, and Azure. With a strong foundation in mathematics and hands-on experience in LLM fine-tuning (LoRA/QLoRA) and vector database integration (Pinecone, ChromaDB), I build robust, production-ready AI solutions that deliver lasting impact. PROFESSIONAL EXPERIENCE Artificial Intelligence Engineer Dolf Technologies Pvt. Ltd 04/2025 - Present •Architected and deployed a conversational Agentic AI system that automated initial resume screening and applicant query handling, reducing recruiter workload by 30%. •Designed and implemented an enterprise-grade RAG pipeline with LangChain + Pinecone, improving recruiter satisfaction scores by 20% through precise, context-aware candidate insights. •Fine-tuned Google Gemini LLM using LoRA for domain-specific talent analysis, enhancing accuracy of candidate qualification matching by 22%. •Deployed the agent as a scalable microservice on AWS using Docker and CI/CD pipelines, ensuring 99.9% uptime and seamless integration into HR platforms. •Established a feedback-driven active learning loop that improved model precision from 84% to 96% in three months based on recruiter- approved training data. •Developed an interactive recruiter dashboard in Streamlit for managing AI agents, reviewing candidate summaries, and tracking hiring KPIs in real time. •Collaborated with the HR analytics team to i"
    },
    "source": "resume",
    "confidence": 95,
    "processingTime": 0
  }
}