{
  "filename": "a1eecb70-7982-4bc1-97cc-945141f412a2.pdf",
  "timestamp": "2025-10-13T12:04:15.739Z",
  "processingTime": 5801,
  "confidence": 80,
  "rawText": "\n\n \nABISHAK.I \nContact \nAddress: \n1/673 East  valasai  street ,pamban, \nRameswaram . pincode-(623521) \n \n \nPhone: \n8489044240  \n \nEmail: \njovialabishak@gmail.com \nLanguages \nEnglish \nTamil \nHobbies \n Writing \n Sketching \n Photography \nSkill Highlights \n Project \nmanagement \n Strong \ndecision \nmaker \n Complex \nproblem \nsolver \n Creative \ndesign \n Innovative \n Service-\nfocused \n \nSummary \nExperienced with all stages of the development cycle for dynamic web \nprojects. Well-versed in numerous programming languages including \nHTML5, PHP, Laravel, JavaScript, bootstrap,CSS, MySQL. Strong \nbackground in project management and customer relations. \nExperience \nAssociate Software Developer- 09/2021 to Till now \nArdhas Technology India Pvt.LTd, Coimbatore \n Cooperate with developer to create clean interfaces and \nsimple, intuitive interactions and experiences. \n Develop project concepts and maintain optimal workflow. \n Work with senior developer to manage large, complex design \nprojects for corporate clients. \n Complete detailed programming and development tasks for \nfront end and internal websites as well as challenging back-end \nserver code. \n Carry out quality assurance tests to discover errors and \noptimize usability. \n \nWeb Developer (Inter)-06/2021 -08/2021 \n Work with senior developer to manage projects for corporate \nclients. \n Complete detailed programming and development tasks for \nfront end and internal websites as well as challenging back-end \nserver code. \nEducation \nK.S.Rangasamy College of Technology ,Namakkal, Tamil Nadu . \nBachelor of Engineering in Mechanical Engineering May 2019  \n CGPA: 7.20/10 \nAdharsh Vidhyalaya Hr. Sec. School , Erode , Tamil Nadu . \nHigher SecondarySchooling May 2015 \n Percentage : 76.33 \nSt.Anne’s Matriculation School ,Rameswaram, Tamil Nadu . \nSSLC Schooling May 2013 \n Percentage : 84 \nProgramming Skill \nPHP Framework:Laravel. \nProgramming Languages: JavaScript, HTML5, PHP, Bootstrap, CSS,  \nMySQL. \n ",
  "extractedData": {
    "name": "ABISHAK.I",
    "email": "jovialabishak@gmail.com",
    "phone": "8489044240",
    "linkedinUrl": null,
    "githubUrl": null,
    "portfolioUrl": null,
    "location": "Rameswaram, Tamil Nadu",
    "title": null,
    "summary": "Experienced with all stages of the development cycle for dynamic web projects. Well-versed in numerous programming languages including HTML5, PHP, Laravel, JavaScript, bootstrap, CSS, MySQL. Strong background in project management and customer relations.",
    "experience": [
      {
        "jobTitle": "Associate Software Developer",
        "company": "Ardhas Technology India Pvt.LTd",
        "duration": "09/2021 to Present",
        "startDate": "2021-09",
        "endDate": "Present",
        "techUsed": [],
        "description": "Cooperate with developer to create clean interfaces and simple, intuitive interactions and experiences. Develop project concepts and maintain optimal workflow. Work with senior developer to manage large, complex design projects for corporate clients. Complete detailed programming and development tasks for front end and internal websites as well as challenging back-end server code. Carry out quality assurance tests to discover errors and optimize usability.",
        "achievements": []
      },
      {
        "jobTitle": "Web Developer (Inter)",
        "company": null,
        "duration": "06/2021 - 08/2021",
        "startDate": "2021-06",
        "endDate": "2021-08",
        "techUsed": [],
        "description": "Work with senior developer to manage projects for corporate clients. Complete detailed programming and development tasks for front end and internal websites as well as challenging back-end server code.",
        "achievements": []
      }
    ],
    "education": [
      {
        "degree": "Bachelor of Engineering",
        "field": "Mechanical Engineering",
        "university": "K.S.Rangasamy College of Technology",
        "year": "2019",
        "percentage": null,
        "gpa": "7.20",
        "location": "Namakkal, Tamil Nadu"
      },
      {
        "degree": "Higher Secondary Schooling",
        "field": null,
        "university": "Adharsh Vidhyalaya Hr. Sec. School",
        "year": "2015",
        "percentage": "76.33",
        "gpa": null,
        "location": "Erode, Tamil Nadu"
      },
      {
        "degree": "SSLC Schooling",
        "field": null,
        "university": "St.Anne’s Matriculation School",
        "year": "2013",
        "percentage": "84",
        "gpa": null,
        "location": "Rameswaram, Tamil Nadu"
      }
    ],
    "projects": [],
    "achievements": [],
    "certifications": [],
    "skills": [
      "Project management",
      "Strong decision maker",
      "Complex problem solver",
      "Creative design",
      "Innovative",
      "Service-focused",
      "PHP",
      "Laravel",
      "JavaScript",
      "HTML5",
      "Bootstrap",
      "CSS",
      "MySQL"
    ],
    "interests": [
      "Writing",
      "Sketching",
      "Photography"
    ],
    "languages": [
      "English",
      "Tamil"
    ],
    "salary": null,
    "availability": null,
    "remotePreference": null,
    "visaStatus": null,
    "originalData": {
      "filename": "a1eecb70-7982-4bc1-97cc-945141f412a2.pdf",
      "rawText": "ABISHAK.I Contact Address: 1/673 East valasai street ,pamban, Rameswaram . pincode-(623521) Phone: 8489044240 Email: jovialabishak@gmail.com Languages English Tamil Hobbies  Writing  Sketching  Photography Skill Highlights  Project management  Strong decision maker  Complex problem solver  Creative design  Innovative  Service- focused Summary Experienced with all stages of the development cycle for dynamic web projects. Well-versed in numerous programming languages including HTML5, PHP, Laravel, JavaScript, bootstrap,CSS, MySQL. Strong background in project management and customer relations. Experience Associate Software Developer- 09/2021 to Till now Ardhas Technology India Pvt.LTd, Coimbatore  Cooperate with developer to create clean interfaces and simple, intuitive interactions and experiences.  Develop project concepts and maintain optimal workflow.  Work with senior developer to manage large, complex design projects for corporate clients.  Complete detailed programming and development tasks for front end and internal websites as well as challenging back-end server code.  Carry out quality assurance tests to discover errors and optimize usability. Web Developer (Inter)-06/2021 -08/2021  Work with senior developer to manage projects for corporate clients.  Complete detailed programming and development tasks for front end and internal websites as well as challenging back-end server code. Education K.S.Rangasamy College of Technology ,Namakkal, Tamil Nadu . Bachelor of Engineering in Mechanical Engineering May 2019  CGPA: 7.20/10 Adharsh Vidhyalaya Hr. Sec. School , Erode , Tamil Nadu . Higher SecondarySchooling May 2015  Percentage : 76.33 St.Anne’s Matriculation School ,Rameswaram, Tamil Nadu . SSLC Schooling May 2013  Percentage : 84 Programming Skill PHP Framework:Laravel. Programming Languages: JavaScript, HTML5, PHP, Bootstrap, CSS, MySQL."
    },
    "source": "resume",
    "confidence": 80,
    "processingTime": 0
  }
}