{
  "filename": "ac96dc26-ea83-41e1-826a-c4a5e235edcb.pdf",
  "timestamp": "2025-09-20T05:42:24.803Z",
  "processingTime": 2003,
  "confidence": 70,
  "rawText": "\n\nSubhash Kumar A\nKasaragod, Kerala\nsubhashka752woj4c_wya@indeedemail.com\n+91 70340 46701\nTo execute my innovative ideas in a challenging field for an organization.\nWilling to relocate: Anywhere\nWork Experience\nPHP Developer\nIntegrated redcherry solution\nJanuary 2022 to July 2022\n• Six months internship with training at Integrated Redcherry\nSolutions Pvt Ltd as PHP Devleoper.\nBiodata:\nName: Subhash Kumar A\nDate of Birth: 25-09-1995\nGender: Male\nNationality: Indian\nEducation\nMaster's in Computer Science\nKannur University - Kerala\nJune 2016 to April 2018\nBachelor's in Computer Science\nKannur University - Kerala\nJune 2013 to May 2016\nHSC in Science\nState board - Kerala\nJune 2011 to March 2013\nSSLC\nState Board\n2011\nSkills / IT Skills\n•Fundamentals of C and C++, Java, php, html.\n•PHP\n\n•MySQL\n•JavaScript\n•HTML5\n•AJAX\n•CSS",
  "extractedData": {
    "name": "Subhash Kumar",
    "email": "subhashka752woj4c_wya@indeedemail.com",
    "portfolioUrl": "https://indeedemail.com",
    "location": "Subhash Kumar A Kasaragod, Kerala subhashka",
    "title": "Subhash Kumar A Kasaragod",
    "experience": [
      {
        "jobTitle": "Subhash Kumar A Kasaragod, Kerala subhashka752woj4c_wya@indeedemail.com +91 70340 46701 To execute my innovative ideas in a challenging field for an organization. Willing to relocate: Anywhere Work Experience PHP Developer Integrated redcherry solution January 2022 to July 2022 • Six months internship with training at Integrated Redcherry Solutions Pvt Ltd as PHP Devleoper. Biodata: Name: Subhash Kumar A Date of Birth: 25-09-1995 Gender: Male Nationality: Indian Education Master's in Computer Science Kannur University - Kerala June 2016 to April 2018 Bachelor's in Computer Science Kannur University - Kerala June 2013 to May 2016 HSC in Science State board - Kerala June 2011 to March 2013 SSLC State Board 2011 Skills / IT Skills •Fundamentals of C and C++, Java, php, html. •PHP •MySQL •JavaScript •HTML5 •AJAX •CSS",
        "company": "Unknown",
        "duration": "Unknown",
        "techUsed": [],
        "description": "Subhash Kumar A Kasaragod, Kerala subhashka752woj4c_wya@indeedemail.com +91 70340 46701 To execute my innovative ideas in a challenging field for an organization. Willing to relocate: Anywhere Work Experience PHP Developer Integrated redcherry solution January 2022 to July 2022 • Six months internship with training at Integrated Redcherry Solutions Pvt Ltd as PHP Devleoper. Biodata: Name: Subhash Kumar A Date of Birth: 25-09-1995 Gender: Male Nationality: Indian Education Master's in Computer Science Kannur University - Kerala June 2016 to April 2018 Bachelor's in Computer Science Kannur University - Kerala June 2013 to May 2016 HSC in Science State board - Kerala June 2011 to March 2013 SSLC State Board 2011 Skills / IT Skills •Fundamentals of C and C++, Java, php, html. •PHP •MySQL •JavaScript •HTML5 •AJAX •CSS"
      }
    ],
    "education": [
      {
        "degree": "Subhash Kumar A Kasaragod, Kerala subhashka752woj4c_wya@indeedemail.com +91 70340 46701 To execute my innovative ideas in a challenging field for an organization. Willing to relocate: Anywhere Work Experience PHP Developer Integrated redcherry solution January 2022 to July 2022 • Six months internship with training at Integrated Redcherry Solutions Pvt Ltd as PHP Devleoper. Biodata: Name: Subhash Kumar A Date of Birth: 25-09-1995 Gender: Male Nationality: Indian Education Master's in Computer Science Kannur University - Kerala June 2016 to April 2018 Bachelor's in Computer Science Kannur University - Kerala June 2013 to May 2016 HSC in Science State board - Kerala June 2011 to March 2013 SSLC State Board 2011 Skills / IT Skills •Fundamentals of C and C++, Java, php, html. •PHP •MySQL •JavaScript •HTML5 •AJAX •CSS",
        "field": "Unknown",
        "university": "Unknown",
        "year": "Unknown"
      }
    ],
    "projects": [],
    "achievements": [],
    "certifications": [],
    "skills": [
      "JavaScript",
      "Java",
      "PHP",
      "HTML",
      "CSS",
      "MySQL"
    ],
    "interests": [],
    "languages": [],
    "originalData": {
      "filename": "ac96dc26-ea83-41e1-826a-c4a5e235edcb.pdf",
      "rawText": "Subhash Kumar A Kasaragod, Kerala subhashka752woj4c_wya@indeedemail.com +91 70340 46701 To execute my innovative ideas in a challenging field for an organization. Willing to relocate: Anywhere Work Experience PHP Developer Integrated redcherry solution January 2022 to July 2022 • Six months internship with training at Integrated Redcherry Solutions Pvt Ltd as PHP Devleoper. Biodata: Name: Subhash Kumar A Date of Birth: 25-09-1995 Gender: Male Nationality: Indian Education Master's in Computer Science Kannur University - Kerala June 2016 to April 2018 Bachelor's in Computer Science Kannur University - Kerala June 2013 to May 2016 HSC in Science State board - Kerala June 2011 to March 2013 SSLC State Board 2011 Skills / IT Skills •Fundamentals of C and C++, Java, php, html. •PHP •MySQL •JavaScript •HTML5 •AJAX •CSS"
    },
    "source": "resume",
    "confidence": 55,
    "processingTime": 0
  }
}