{
  "filename": "cc444fc2-d6b2-42aa-93be-fe3de7025093.pdf",
  "timestamp": "2025-10-11T05:39:41.791Z",
  "processingTime": 4840,
  "confidence": 92,
  "rawText": "\n\nC O N T A C T\n9008809443\ndivyasbhaskar11@gmail.com\nBangalore\nwww.linkedin.com/in/divyabhaskar\n11\nSRI SIDDHARTHA INSTITUTE OF\nTECHNOLOGY\nBachelor of Engineering - ISE\nGPA: 6.9\n2016 - 2020\nE D U C A T I O N\nS K I L L S\nProgramming & Frameworks: C#, .NET\n(.NET Core / ASP.NET), MVC, Entity\nFramework, SQL\nFrontend: React.js, HTML, CSS\nCloud & DevOps: AWS, AWS CDK, basic\nCI/CD\nTesting & Quality: Unit Testing, SOLID\nprinciples, code reviews\nTools & Methodologies: Agile (Scrum),\nFigma (implementing designs), Visual\nStudio, Git\nEnglish\nKannada\nHindi\nL A N G U A G E S\nP R O F I L E   S U M M A R Y\nResults-driven .NET Developer with over 4.5 years of hands-on experience in\ndeveloping  and  maintaining  scalable  applications  using  the  .NET  framework.\nAdept at building robust backend solutions complemented by 1 year of practical\nexperience in React.js for modern, responsive front-end development. Proven\nability to translate business requirements into efficient technical solutions. \nW O R K   E X P E R I E N C E\nJULY 2023 - PRESENT\nDiligent Corporation —Software Engineer\nProject - POLICY MANAGER - - IT CONSOLIDATES DOCUMENT MANAGEMENT\nACTIVITIES TO SIMPLIFY AND ENSURE ADHERENCE\nMARCH 2021 -  JULY 2023 \nApexon —Associate Software Engineer\nProject - EPOST GLOBAL - EPOST GLOBAL'S INTERNATIONAL PARCEL AND MAIL\nSHIPPING ALLOW BUSINESSES TO STREAMLINE GLOBAL DISTRIBUTION WHILE\nINCREASING CUSTOMER SATISFACTION\nIntegrated MS Word Editor (WOPI) with Policy Manager for seamless in-browser editing,\nboosting document handling efficiency by 50–80%.\nDeveloped public access for Policy Portal, ensuring secure access to only public documents,\nimproving compliance by 30%.\nEnhanced  system  security  by  resolving  15+  critical  bugs  and  vulnerabilities,  reducing\nriskDeveloped  public  access  for  Policy  Portal,  ensuring  secure  access  to  only  public\ndocuments,\nincidents by 40% improving compliance by 30%.\nIntegrated MS Word Editor (WOPI) with Policy Manager for seamless in-browser editing,\nboosting\ndocument handling efficiency by 50–80%.\nEnhanced system security by resolving 15+ critical bugs and vulnerabilities, reducing risk\nWorked with the engineering team to exercise best practices in the software\ndevelopment life cycle and identify improvements to existing software.\nExperience of working in the end-to-end software development lifecycle and\npresenting innovative solutions to meet client needs.\nExperience in developing and directing bug free software system validation,\ntesting methods a software programming initiative \nAdmirable  communication  ,interpersonal,  analytical  and  critical  thinking,\nproblem-solving  a  collaboration  skills  with  an  aptitude  to  work  across  all\nlevels of management and different disciplines.\nAnalyzing  new  requirements  and  providing  impact  analysis  addressing\ntechnical design a identifying individual tasks.\nDIVYA SALOMON\nSoftware Engineer\nS T R E N G T H S\nDedicated team player with communication skills. \nI have the follow through and positive attitude that will allow me to achieve\ncompany targets",
  "extractedData": {
    "name": "Divya Salomon",
    "email": "divyasbhaskar11@gmail.com",
    "phone": "9008809443",
    "linkedinUrl": "https://www.linkedin.com/in/divyabhaskar",
    "githubUrl": null,
    "portfolioUrl": null,
    "location": "Bangalore",
    "title": "Software Engineer",
    "summary": "Results-driven .NET Developer with over 4.5 years of hands-on experience in developing and maintaining scalable applications using the .NET framework. Adept at building robust backend solutions complemented by 1 year of practical experience in React.js for modern, responsive front-end development. Proven ability to translate business requirements into efficient technical solutions.",
    "experience": [
      {
        "jobTitle": "Software Engineer",
        "company": "Diligent Corporation",
        "duration": "July 2023 - Present",
        "startDate": "2023-07",
        "endDate": "Present",
        "techUsed": [],
        "description": "Project - POLICY MANAGER - IT CONSOLIDATES DOCUMENT MANAGEMENT ACTIVITIES TO SIMPLIFY AND ENSURE ADHERENCE",
        "achievements": []
      },
      {
        "jobTitle": "Associate Software Engineer",
        "company": "Apexon",
        "duration": "March 2021 - July 2023",
        "startDate": "2021-03",
        "endDate": "2023-07",
        "techUsed": [],
        "description": "Project - EPOST GLOBAL - EPOST GLOBAL'S INTERNATIONAL PARCEL AND MAIL SHIPPING ALLOW BUSINESSES TO STREAMLINE GLOBAL DISTRIBUTION WHILE INCREASING CUSTOMER SATISFACTION",
        "achievements": [
          "Integrated MS Word Editor (WOPI) with Policy Manager for seamless in-browser editing, boosting document handling efficiency by 50–80%.",
          "Developed public access for Policy Portal, ensuring secure access to only public documents, improving compliance by 30%.",
          "Enhanced system security by resolving 15+ critical bugs and vulnerabilities, reducing risk incidents by 40%."
        ]
      }
    ],
    "education": [
      {
        "degree": "Bachelor of Engineering",
        "field": "Information Science and Engineering",
        "university": "Sri Siddhartha Institute of Technology",
        "year": "2020",
        "percentage": null,
        "gpa": "6.9",
        "location": null
      }
    ],
    "projects": [],
    "achievements": [],
    "certifications": [],
    "skills": [
      "C#",
      ".NET",
      ".NET Core",
      "ASP.NET",
      "MVC",
      "Entity Framework",
      "SQL",
      "React.js",
      "HTML",
      "CSS",
      "AWS",
      "AWS CDK",
      "CI/CD",
      "Unit Testing",
      "SOLID principles",
      "code reviews",
      "Agile (Scrum)",
      "Figma",
      "Visual Studio",
      "Git"
    ],
    "interests": [],
    "languages": [
      "English",
      "Kannada",
      "Hindi"
    ],
    "salary": null,
    "availability": null,
    "remotePreference": null,
    "visaStatus": null,
    "originalData": {
      "filename": "cc444fc2-d6b2-42aa-93be-fe3de7025093.pdf",
      "rawText": "C O N T A C T 9008809443 divyasbhaskar11@gmail.com Bangalore www.linkedin.com/in/divyabhaskar 11 SRI SIDDHARTHA INSTITUTE OF TECHNOLOGY Bachelor of Engineering - ISE GPA: 6.9 2016 - 2020 E D U C A T I O N S K I L L S Programming & Frameworks: C#, .NET (.NET Core / ASP.NET), MVC, Entity Framework, SQL Frontend: React.js, HTML, CSS Cloud & DevOps: AWS, AWS CDK, basic CI/CD Testing & Quality: Unit Testing, SOLID principles, code reviews Tools & Methodologies: Agile (Scrum), Figma (implementing designs), Visual Studio, Git English Kannada Hindi L A N G U A G E S P R O F I L E S U M M A R Y Results-driven .NET Developer with over 4.5 years of hands-on experience in developing and maintaining scalable applications using the .NET framework. Adept at building robust backend solutions complemented by 1 year of practical experience in React.js for modern, responsive front-end development. Proven ability to translate business requirements into efficient technical solutions. W O R K E X P E R I E N C E JULY 2023 - PRESENT Diligent Corporation —Software Engineer Project - POLICY MANAGER - - IT CONSOLIDATES DOCUMENT MANAGEMENT ACTIVITIES TO SIMPLIFY AND ENSURE ADHERENCE MARCH 2021 - JULY 2023 Apexon —Associate Software Engineer Project - EPOST GLOBAL - EPOST GLOBAL'S INTERNATIONAL PARCEL AND MAIL SHIPPING ALLOW BUSINESSES TO STREAMLINE GLOBAL DISTRIBUTION WHILE INCREASING CUSTOMER SATISFACTION Integrated MS Word Editor (WOPI) with Policy Manager for seamless in-browser editing, boosting document handling efficiency by 50–80%. Developed public access for Policy Portal, ensuring secure access to only public documents, improving compliance by 30%. Enhanced system security by resolving 15+ critical bugs and vulnerabilities, reducing riskDeveloped public access for Policy Portal, ensuring secure access to only public documents, incidents by 40% improving compliance by 30%. Integrated MS Word Editor (WOPI) with Policy Manager for seamless in-browser editing, boosting document handling "
    },
    "source": "resume",
    "confidence": 92,
    "processingTime": 0
  }
}