{
  "filename": "CV_2025063016530885.pdf",
  "timestamp": "2025-09-03T12:46:50.827Z",
  "processingTime": 2876,
  "confidence": 70,
  "rawText": "\n\n2025\n2022\n2020\nBidulata Sahani\nChhandamund,Jari, Jajpur,odisha,755016\n7205944695 | bidulatasahani2004@gmail.com\nObjective\nSeeking a challenging entry-level position to utilize my skills and contribute to the success of a dynamic team.\nEducation\nKharasrota degree college, Singhpur,Jajpur\nBA in Education\nCGPA 8.27 ,77.70%\nKharasrota Higher secondary school, Singhpur\nCHSE\n405,67.5%\nBCJ High school, chhandamund\nBSE\n251,41.83%\nSkills\nPGDCA\nLanguages\nHindi English Odia\nPersonal Details\nDate of Birth:26/11/2004\nNationality:Indian\nFather's Name:Bijaya Sahani\nHobbies:Writting\nPermanent address ::Chhandamund, Jari, Jajpur, Odisha,755016\nDeclaration\nI here by declared that above mentioned particulars are true of my knowledge and belief .\nName :\nPlace :",
  "extractedData": {
    "name": "Bidulata Sahani",
    "email": "bidulatasahani2004@gmail.com",
    "phone": "7205944695",
    "linkedinUrl": null,
    "githubUrl": null,
    "portfolioUrl": null,
    "location": "Chhandamund, Jari, Jajpur, Odisha, 755016",
    "title": null,
    "summary": "Seeking a challenging entry-level position to utilize my skills and contribute to the success of a dynamic team.",
    "experience": [],
    "education": [
      {
        "degree": "BA",
        "field": "Education",
        "university": "Kharasrota Degree College, Singhpur, Jajpur",
        "year": null,
        "percentage": "77.70%",
        "gpa": "8.27",
        "location": "Singhpur, Jajpur"
      },
      {
        "degree": "CHSE",
        "field": null,
        "university": "Kharasrota Higher Secondary School, Singhpur",
        "year": null,
        "percentage": "67.5%",
        "gpa": null,
        "location": "Singhpur"
      },
      {
        "degree": "BSE",
        "field": null,
        "university": "BCJ High School, Chhandamund",
        "year": null,
        "percentage": "41.83%",
        "gpa": null,
        "location": "Chhandamund"
      }
    ],
    "projects": [],
    "achievements": [],
    "certifications": [],
    "skills": [
      "PGDCA"
    ],
    "interests": [
      "Writing"
    ],
    "languages": [
      "Hindi",
      "English",
      "Odia"
    ],
    "originalData": {
      "filename": "CV_2025063016530885.pdf",
      "rawText": "2025 2022 2020 Bidulata Sahani Chhandamund,Jari, Jajpur,odisha,755016 7205944695 | bidulatasahani2004@gmail.com Objective Seeking a challenging entry-level position to utilize my skills and contribute to the success of a dynamic team. Education Kharasrota degree college, Singhpur,Jajpur BA in Education CGPA 8.27 ,77.70% Kharasrota Higher secondary school, Singhpur CHSE 405,67.5% BCJ High school, chhandamund BSE 251,41.83% Skills PGDCA Languages Hindi English Odia Personal Details Date of Birth:26/11/2004 Nationality:Indian Father's Name:Bijaya Sahani Hobbies:Writting Permanent address ::Chhandamund, Jari, Jajpur, Odisha,755016 Declaration I here by declared that above mentioned particulars are true of my knowledge and belief . Name : Place :"
    },
    "source": "resume",
    "confidence": 70,
    "processingTime": 0
  }
}