{
  "filename": "CV_Mahesh__Konchada 12.pdf",
  "timestamp": "2025-09-03T08:11:37.111Z",
  "processingTime": 13548,
  "confidence": 95,
  "rawText": "\n\nMahesh Konchada Contact: +91-9642971300 \nLinkedIn: https://www.linkedin.com/in/mahesh-konchada-996985150/ E-Mail: mkonchada0@gmail.com \n \n Profile Summary  \nResults-driven  Business  Analyst  with  a  strategic  blend  of  analytical  capabilities  and  stakeholder  management \nexpertise.  Combining  a  strong  Computer  Science  foundation  with  proven  experience  in  data-driven  decision \nmaking,  requirements  analysis,  and  business  process  optimization.  Demonstrated  excellence  in  extracting \nactionable  insights  from  data,  translating  business  needs  into  technical  solutions,  and  communicating  complex \nconcepts  to  diverse  audiences.  At  Asian  Paints,  I  leveraged  data  visualization  techniques  to  identify  growth \nopportunities and optimize territory performance through analytical dashboards. At Semiconsoul Technologies, I \nbridged  technical  teams  and  business  stakeholders  by  translating  intricate  technological  capabilities  into  clear \nbusiness benefits. I excel in ambiguous environments, approaching challenges with analytical rigor and strategic \nthinking to deliver measurable business impact. \nOrganizational Experience:   \nStrategic Account Partner, Andolasoft Feb 2025- Present \n• Requirements Analysis & Solution Design: Analyzed client business needs across CRM, project \nmanagement, and construction tool implementations, translating requirements into optimized solutions \n• Data-Driven Client Acquisition: Employed market analysis to identify and acquire high-value enterprise \nclients across diverse product categories, exceeding quarterly targets \n• Stakeholder Communication: Developed comprehensive documentation and presentations for all \nlevels of client organizations, from operational teams to C-suite executives \n• Process Optimization: Streamlined client onboarding workflows, resulting in faster implementation and \nimproved user adoption rates \n• Cross-Functional Collaboration: Identified strategic business opportunities through analysis of customer \nfeedback and market trends, developing data-backed product improvement recommendation \n \nASSISTANT MANAGEMENT TRAINEE, ASIAN PAINTS MAY 2024- NOV 2024 \n• Leading a team of 5 across five territories, managing 600+ dealers and driving month-on-month sales growth \nthrough data-driven strategies. \n• Conducted market analyses leveraging data visualization techniques to identify growth opportunities, \nusing insights to open new dealerships and expand market presence. \n• Spearheaded the creation of interactive dashboards visualizing key performance indicators and territory \nsales trends, enabling real-time monitoring of 600+ dealers and data-driven course correction strategies. \n• Implemented data-driven solutions to optimize sales processes, improve dealer payment cycles, and enhance \noverall territory performance. \n• Managed team performance through data-backed insights, setting targeted goals and providing analytical \ntools to improve efficiency. \nMANAGEMENT TRAINEE, SEMICONSOUL TECHNOLOGIES PRIVATE LTD. FEB 2020 – JULY 2021 \n• Pre-Sales and Solution Design: Collaborated with development teams to design comprehensive IoT solutions \nacross Healthcare, Smart Factories, and Urban Infrastructure technologies \n• Technical Pitch Presentations: Developed and delivered compelling presentations showcasing IoT gateway \nmiddleware, device handling platforms, and transformative digital technologies \n• Solution Proposals and Documentation: Created detailed technical documentation addressing complex \ntechnological requirements in Indoor Tracking, Asset Monitoring, and Industrial IoT \n• Stakeholder Engagement: Served as a critical bridge between technical teams and business users, translating \nintricate technological capabilities into clear business benefits \n• Developed strategic solution proposals for diverse domains including Defence Electronics, Smart Cities, and \nIoT Gateway technologies, demonstrating expertise in innovative technological solutions \n\n \nMaster of Business Administration in Marketing and Systems, Minor in strategy \nXavier Institute of Management • Bhubaneshwar • 2024 \nBachelor of Technology (Computer science and engineering) \nSri Venkateswara university college of engineering • TIRUPATI • 2019 \n \nIT Skills  \n \n• Data Management: DBMS (MySQL) \n• Languages: C, Python, SQL \n• AI Prompt Engineering \n• Visualization: Power BI & Tableau \n• Other Tools: MS PowerPoint, MS Excel, Orangescrum (Project Management), CRM Leaf \n \nInternships  \nKotak Mahindra Bank Ltd. -2023 \n• Analyzed competitor offerings and customer behavior to propose differentiated strategies for expanding \nportfolio \n• Conducted comprehensive market research to identify potential growth areas in two-wheeler financing \nindustry \n• Conducted customer surveys that yielded insights which were used to develop customer centric financing \nsolutions \n• Identified and addressed key pain points in two-wheeler loan applications resulting in a reduction in TAT \nArchon Motors -2023 \n• Conducted Marketing research to collect and analyze data to get insights about customer perception \n• Ideated customer engagement programs, loyalty initiatives and after sales support strategies \nACV Tourism - 2023 \n• Developed a brief 1-year Marketing Plan including the cost associated and Manpower required \n• Evaluated and optimized marketing channels, including social media to maximize reach \n \nOutlook Group -2022 \n• Successfully pitched and sold outlook products to diverse customers and ensured customer retention \n• Collaborated with Marketing team to develop targeted sales campaigns, resulting in increase in sales \n \nFrienden Management -2019 \n• Scheduled events, built relationships with potential clients and suggested inputs regarding marketing \n• Assisted themanagement in creating engaging content and managed company’s socialmedia and blogs \n \nInternshala -2018 \n• Generated Leads by promoting Internshala brand, products, and their services \n• Hosted events like workshops, seminars, events and built relationships with students and faculty \nMajor Certifications  \n• AI Product Management Specialization by Duke University, Coursera 2024 \n• IT Presales Management Masterclass, Udemy 2024 \n• Certified in Marketing Research and Consumer Behavior, Coursera 2022 \n• Certified in Positioning: What you need for a Successful Marketing Strategy, Coursera 2022 \n• Certified in Fundamentals of Digital Marketing, Google 2020 \nAcademic Details ",
  "extractedData": {
    "name": "Mahesh Konchada",
    "email": "mkonchada0@gmail.com",
    "phone": "+91-9642971300",
    "linkedinUrl": "https://www.linkedin.com/in/mahesh-konchada-996985150/",
    "githubUrl": null,
    "portfolioUrl": null,
    "location": null,
    "title": "Strategic Account Partner",
    "summary": "Results-driven Business Analyst with a strategic blend of analytical capabilities and stakeholder management expertise. Combining a strong Computer Science foundation with proven experience in data-driven decision making, requirements analysis, and business process optimization. Demonstrated excellence in extracting actionable insights from data, translating business needs into technical solutions, and communicating complex concepts to diverse audiences.",
    "experience": [
      {
        "jobTitle": "Strategic Account Partner",
        "company": "Andolasoft",
        "duration": "Feb 2025 - Present",
        "startDate": "2025-02",
        "endDate": "Present",
        "techUsed": [],
        "description": "Analyzed client business needs across CRM, project management, and construction tool implementations, translating requirements into optimized solutions. Employed market analysis to identify and acquire high-value enterprise clients across diverse product categories, exceeding quarterly targets. Developed comprehensive documentation and presentations for all levels of client organizations, from operational teams to C-suite executives. Streamlined client onboarding workflows, resulting in faster implementation and improved user adoption rates. Identified strategic business opportunities through analysis of customer feedback and market trends, developing data-backed product improvement recommendation.",
        "achievements": []
      },
      {
        "jobTitle": "Assistant Management Trainee",
        "company": "Asian Paints",
        "duration": "May 2024 - Nov 2024",
        "startDate": "2024-05",
        "endDate": "2024-11",
        "techUsed": [
          "Data Visualization"
        ],
        "description": "Leading a team of 5 across five territories, managing 600+ dealers and driving month-on-month sales growth through data-driven strategies. Conducted market analyses leveraging data visualization techniques to identify growth opportunities, using insights to open new dealerships and expand market presence. Spearheaded the creation of interactive dashboards visualizing key performance indicators and territory sales trends, enabling real-time monitoring of 600+ dealers and data-driven course correction strategies. Implemented data-driven solutions to optimize sales processes, improve dealer payment cycles, and enhance overall territory performance. Managed team performance through data-backed insights, setting targeted goals and providing analytical tools to improve efficiency.",
        "achievements": []
      },
      {
        "jobTitle": "Management Trainee",
        "company": "Semiconsoul Technologies Private Ltd.",
        "duration": "Feb 2020 - July 2021",
        "startDate": "2020-02",
        "endDate": "2021-07",
        "techUsed": [
          "IoT"
        ],
        "description": "Collaborated with development teams to design comprehensive IoT solutions across Healthcare, Smart Factories, and Urban Infrastructure technologies. Developed and delivered compelling presentations showcasing IoT gateway middleware, device handling platforms, and transformative digital technologies. Created detailed technical documentation addressing complex technological requirements in Indoor Tracking, Asset Monitoring, and Industrial IoT. Served as a critical bridge between technical teams and business users, translating intricate technological capabilities into clear business benefits. Developed strategic solution proposals for diverse domains including Defence Electronics, Smart Cities, and IoT Gateway technologies, demonstrating expertise in innovative technological solutions.",
        "achievements": []
      }
    ],
    "education": [
      {
        "degree": "Master of Business Administration",
        "field": "Marketing and Systems, Minor in Strategy",
        "university": "Xavier Institute of Management",
        "year": "2024",
        "percentage": null,
        "gpa": null,
        "location": "Bhubaneshwar"
      },
      {
        "degree": "Bachelor of Technology",
        "field": "Computer Science and Engineering",
        "university": "Sri Venkateswara University College of Engineering",
        "year": "2019",
        "percentage": null,
        "gpa": null,
        "location": "Tirupati"
      }
    ],
    "projects": [],
    "achievements": [],
    "certifications": [
      {
        "name": "AI Product Management Specialization",
        "issuer": "Duke University, Coursera",
        "date": "2024",
        "expiryDate": null,
        "credentialId": null,
        "url": null
      },
      {
        "name": "IT Presales Management Masterclass",
        "issuer": "Udemy",
        "date": "2024",
        "expiryDate": null,
        "credentialId": null,
        "url": null
      },
      {
        "name": "Certified in Marketing Research and Consumer Behavior",
        "issuer": "Coursera",
        "date": "2022",
        "expiryDate": null,
        "credentialId": null,
        "url": null
      },
      {
        "name": "Certified in Positioning: What you need for a Successful Marketing Strategy",
        "issuer": "Coursera",
        "date": "2022",
        "expiryDate": null,
        "credentialId": null,
        "url": null
      },
      {
        "name": "Certified in Fundamentals of Digital Marketing",
        "issuer": "Google",
        "date": "2020",
        "expiryDate": null,
        "credentialId": null,
        "url": null
      }
    ],
    "skills": [
      "DBMS (MySQL)",
      "C",
      "Python",
      "SQL",
      "AI Prompt Engineering",
      "Power BI",
      "Tableau",
      "MS PowerPoint",
      "MS Excel",
      "Orangescrum",
      "CRM Leaf"
    ],
    "interests": [],
    "languages": [],
    "originalData": {
      "filename": "CV_Mahesh__Konchada 12.pdf",
      "rawText": "Mahesh Konchada Contact: +91-9642971300 LinkedIn: https://www.linkedin.com/in/mahesh-konchada-996985150/ E-Mail: mkonchada0@gmail.com Profile Summary Results-driven Business Analyst with a strategic blend of analytical capabilities and stakeholder management expertise. Combining a strong Computer Science foundation with proven experience in data-driven decision making, requirements analysis, and business process optimization. Demonstrated excellence in extracting actionable insights from data, translating business needs into technical solutions, and communicating complex concepts to diverse audiences. At Asian Paints, I leveraged data visualization techniques to identify growth opportunities and optimize territory performance through analytical dashboards. At Semiconsoul Technologies, I bridged technical teams and business stakeholders by translating intricate technological capabilities into clear business benefits. I excel in ambiguous environments, approaching challenges with analytical rigor and strategic thinking to deliver measurable business impact. Organizational Experience: Strategic Account Partner, Andolasoft Feb 2025- Present • Requirements Analysis & Solution Design: Analyzed client business needs across CRM, project management, and construction tool implementations, translating requirements into optimized solutions • Data-Driven Client Acquisition: Employed market analysis to identify and acquire high-value enterprise clients across diverse product categories, exceeding quarterly targets • Stakeholder Communication: Developed comprehensive documentation and presentations for all levels of client organizations, from operational teams to C-suite executives • Process Optimization: Streamlined client onboarding workflows, resulting in faster implementation and improved user adoption rates • Cross-Functional Collaboration: Identified strategic business opportunities through analysis of customer feedback and market trends, developing data-backed product impro"
    },
    "source": "resume",
    "confidence": 95,
    "processingTime": 0
  }
}