{
  "filename": "d3166a8d-9eca-4590-a5d3-dc9940cff461.pdf",
  "timestamp": "2025-09-29T08:58:54.308Z",
  "processingTime": 3896,
  "confidence": 75,
  "rawText": "\n\nCURRICULUM VITAE \n \nE-mail: rajeerajeswari640@gmail.com \nhttps://github.com/Rajeswari640 \nRAJESWARI.N Mobile: +91 9346543414 \n \n Objective : \nImmediate  Joiner.  Looking  for  better  opportunity  as  a  Python Developer.  Fresher  with  BSC \n(maths, Physics & Computer science) currently living in Bengaluru. To secure a challenging position \nin a  reputable  organization  to  expand  my  knowledge  and  skills.  I  sincerely  believe  that  only  hard \nwork and dedication towards the work entrusted will lead a person to reach the goal of success. \n Education Qualification: \nDegree \nInstitution Score \nB.Sc \n(Mathematics, Physics & computer \nscience) \nIndira Rajiv memorial(IRM) \nDegree College - Kuppam \n8.3/10 CGPA(2022) \nBoard of Intermediate Education, \nAP \nKuppam junior  College - \nKuppam \n8.34/10 CGPA(2019) \nS.S.C from Board of Secondary \nEducation, AP \nZ.P. High.School \n-Settipalli \n8.2/10 CGPA(2017) \n \n Professional Skills: \n. PYTHON (Full stack Developer) \n Good Knowledge in Core & Advance Python programming language with DJANGO Framework.\n Very Good knowledge in Fundamentals, Collections, Data Types, Statements, Functions, Modules.\n Good knowledge on Front-End Technologies like HTML, CSS, JS, Bootstrap.\n Good Knowlwdge MYSQL Database.\n Good in communication, coordinate with team and skill improvement.\n \n Technical Skills: \n Operating System : Windows Family\n Languages : PYTHON (Fullstack)\n Web Technologies : HTML, CSS, Bootstrap, Javascript, Django.\n Databases : MYSQL-server\n \n Project Details: \nProject Name : PORTFOLIO\n\nInstitute :  Fresherslabs \nRole : Software Developer \nLanguages Used : Python. \n     Web Technologies Used : HTML, CSS, BOOTSTRAP. \nTools used : Visual studio code. \n \nDescription:  \nMy  portfolio  is  a  responsive  web  application  that  typically  shows  my  personal  and  professional \ndetails. Developed this portfolio using HTML, CSS, Bootstrap . \n \n Strengths: \n Hard working and confident. Ability to work well under pressure\n Result oriented Ability to achieve the target within given time and coordination and team \nworking skills.\n Willingness and ability to adapt the changing situations and ability to handle multiple \nresponsibilities.\n \n Professional Info: \nName :                  RAJESWARI.N \nFather Name : Narayana \n Gender : Female \nDate of birth : 10 march 2002 \nNationality : Indian \nLanguages Known : English , Telugu,Kannada \nHobbies : playing cricket and chess , listening music. \nPermanent Address : Kadiyalanagar, PES post, Gudupalli(mandal), Chittoor AP-517525 . \n \n Declaration: \nI do hereby declare that the information stated above is true to the best of my knowledge. \n \nPlace: \nDate: \n(Rajeswari N) ",
  "extractedData": {
    "name": "RAJESWARI.N",
    "email": "rajeerajeswari640@gmail.com",
    "phone": "+91 9346543414",
    "linkedinUrl": null,
    "githubUrl": "https://github.com/Rajeswari640",
    "portfolioUrl": null,
    "location": "Bengaluru",
    "title": null,
    "summary": "Immediate Joiner. Looking for better opportunity as a Python Developer. Fresher with BSC (maths, Physics & Computer science) currently living in Bengaluru. To secure a challenging position in a reputable organization to expand my knowledge and skills. I sincerely believe that only hard work and dedication towards the work entrusted will lead a person to reach the goal of success.",
    "experience": [],
    "education": [
      {
        "degree": "B.Sc",
        "field": "Mathematics, Physics & Computer Science",
        "university": "Indira Rajiv memorial(IRM) Degree College",
        "year": "2022",
        "percentage": null,
        "gpa": "8.3/10",
        "location": "Kuppam"
      }
    ],
    "projects": [
      {
        "name": "PORTFOLIO",
        "description": "My portfolio is a responsive web application that typically shows my personal and professional details. Developed this portfolio using HTML, CSS, Bootstrap.",
        "techUsed": [
          "Python",
          "HTML",
          "CSS",
          "Bootstrap"
        ],
        "duration": null,
        "url": null,
        "achievements": []
      }
    ],
    "achievements": [],
    "certifications": [],
    "skills": [
      "PYTHON (Full stack Developer)",
      "Core & Advance Python",
      "DJANGO Framework",
      "HTML",
      "CSS",
      "JS",
      "Bootstrap",
      "MYSQL Database"
    ],
    "interests": [
      "playing cricket",
      "chess",
      "listening music"
    ],
    "languages": [
      "English",
      "Telugu",
      "Kannada"
    ],
    "salary": null,
    "availability": "Immediate",
    "remotePreference": null,
    "visaStatus": null,
    "originalData": {
      "filename": "d3166a8d-9eca-4590-a5d3-dc9940cff461.pdf",
      "rawText": "CURRICULUM VITAE E-mail: rajeerajeswari640@gmail.com https://github.com/Rajeswari640 RAJESWARI.N Mobile: +91 9346543414  Objective : Immediate Joiner. Looking for better opportunity as a Python Developer. Fresher with BSC (maths, Physics & Computer science) currently living in Bengaluru. To secure a challenging position in a reputable organization to expand my knowledge and skills. I sincerely believe that only hard work and dedication towards the work entrusted will lead a person to reach the goal of success.  Education Qualification: Degree Institution Score B.Sc (Mathematics, Physics & computer science) Indira Rajiv memorial(IRM) Degree College - Kuppam 8.3/10 CGPA(2022) Board of Intermediate Education, AP Kuppam junior College - Kuppam 8.34/10 CGPA(2019) S.S.C from Board of Secondary Education, AP Z.P. High.School -Settipalli 8.2/10 CGPA(2017)  Professional Skills: . PYTHON (Full stack Developer)  Good Knowledge in Core & Advance Python programming language with DJANGO Framework.  Very Good knowledge in Fundamentals, Collections, Data Types, Statements, Functions, Modules.  Good knowledge on Front-End Technologies like HTML, CSS, JS, Bootstrap.  Good Knowlwdge MYSQL Database.  Good in communication, coordinate with team and skill improvement.  Technical Skills:  Operating System : Windows Family  Languages : PYTHON (Fullstack)  Web Technologies : HTML, CSS, Bootstrap, Javascript, Django.  Databases : MYSQL-server  Project Details: Project Name : PORTFOLIO Institute : Fresherslabs Role : Software Developer Languages Used : Python. Web Technologies Used : HTML, CSS, BOOTSTRAP. Tools used : Visual studio code. Description: My portfolio is a responsive web application that typically shows my personal and professional details. Developed this portfolio using HTML, CSS, Bootstrap .  Strengths:  Hard working and confident. Ability to work well under pressure  Result oriented Ability to achieve the target within given time and coordination and "
    },
    "source": "resume",
    "confidence": 75,
    "processingTime": 0
  }
}