{
  "filename": "Diptimayee_Resume-1-1-1.pdf",
  "timestamp": "2025-09-03T13:47:10.547Z",
  "processingTime": 5183,
  "confidence": 86,
  "rawText": "\n\nSKILLS\nLANGUAGES\nPROJECT\nDIPTIMAYEE NAYAK\nSOFTWARE DEVELOPER\nCONTACT\n9777903585\ndiptimayeen223@gmail.com\nSailashree Vihar, Bhubaneswar,\nOdisha, PIN- 751021\nHOBBIES\nTravelling\nDancing\nPainting\nWeb Development: HTML,CSS,\nJavascript,React,AngularJs.\nProgramming Language: C,Java.\nDatabase: MongoDB,SQL.\nPROFESSIONAL SUMMARY\nMASTER OF COMPUTER APPLICATION(MCA)(2022-2024)\nTrident Accademy Of Creative Techonology,Bhubaneswar.\nBACHELOR OF SCIENCE(BSC)\nOdia\nEnglish\nHindi\nINTERESTS\nCooking\nGardening\nCreative activities\nHandicraft\nCERTIFICATION\nManagement Information\nSystem. \nIntroduction to industry 4.0.\nIntellectual property.\nInternship certificate from\nJavaCEnterpriser Pvt.Ltd\nPROTTTGRAMMING GUAGE: C,JA\nEDUCATION\nDatabase: MongoDB,SQL.\nSS\nSession:2022-2024\nINTERMEDIATE\nCredential college of commerce and science,Bhadrak\nSession:2016-2018\nMATRICULATION\nSoso Govt Girls High School,soso\nHighly motivated and dynamic professional seeking a challenging\nposition in the techonology industry when i can leverage my\nknowledge of emerging techonologies.\nHEART DISEASE PREDICTION SYSTEM\nDECLARATION\nI hereby declare that all the details mentioned above are in\naccordance with the truth and fact as per my knowledge and i hold\nthe responsibility for the correctness of the above-mentioned\nparticulars.\nBuilt a heart disease prediction system by analysing patient data to\npredict the likelihood of heart disease based on various health metrics.\nTechonology used:Python\nAgarapara College,Agarapara(Fakir Mohan University,Balasore",
  "extractedData": {
    "name": "Diptimayee Nayak",
    "email": "diptimayeen223@gmail.com",
    "phone": "9777903585",
    "linkedinUrl": null,
    "githubUrl": null,
    "portfolioUrl": null,
    "location": "Sailashree Vihar, Bhubaneswar, Odisha, PIN- 751021",
    "title": "Software Developer",
    "summary": "Highly motivated and dynamic professional seeking a challenging position in the technology industry where I can leverage my knowledge of emerging technologies.",
    "experience": [],
    "education": [
      {
        "degree": "Master of Computer Application",
        "field": null,
        "university": "Trident Academy Of Creative Technology",
        "year": "2024",
        "percentage": null,
        "gpa": null,
        "location": "Bhubaneswar"
      },
      {
        "degree": "Bachelor of Science",
        "field": null,
        "university": "Agarapara College, Fakir Mohan University",
        "year": null,
        "percentage": null,
        "gpa": null,
        "location": "Balasore"
      },
      {
        "degree": "Intermediate",
        "field": null,
        "university": "Credential College of Commerce and Science",
        "year": "2018",
        "percentage": null,
        "gpa": null,
        "location": "Bhadrak"
      },
      {
        "degree": "Matriculation",
        "field": null,
        "university": "Soso Govt Girls High School",
        "year": null,
        "percentage": null,
        "gpa": null,
        "location": "Soso"
      }
    ],
    "projects": [
      {
        "name": "Heart Disease Prediction System",
        "description": "Built a heart disease prediction system by analysing patient data to predict the likelihood of heart disease based on various health metrics.",
        "techUsed": [
          "Python"
        ],
        "duration": null,
        "url": null,
        "achievements": []
      }
    ],
    "achievements": [],
    "certifications": [
      {
        "name": "Management Information System",
        "issuer": null,
        "date": null,
        "expiryDate": null,
        "credentialId": null,
        "url": null
      },
      {
        "name": "Introduction to Industry 4.0",
        "issuer": null,
        "date": null,
        "expiryDate": null,
        "credentialId": null,
        "url": null
      },
      {
        "name": "Intellectual Property",
        "issuer": null,
        "date": null,
        "expiryDate": null,
        "credentialId": null,
        "url": null
      },
      {
        "name": "Internship Certificate",
        "issuer": "JavaCEnterpriser Pvt. Ltd",
        "date": null,
        "expiryDate": null,
        "credentialId": null,
        "url": null
      }
    ],
    "skills": [
      "HTML",
      "CSS",
      "JavaScript",
      "React",
      "AngularJs",
      "C",
      "Java",
      "MongoDB",
      "SQL"
    ],
    "interests": [
      "Cooking",
      "Gardening",
      "Creative activities",
      "Handicraft"
    ],
    "languages": [
      "Odia",
      "English",
      "Hindi"
    ],
    "originalData": {
      "filename": "Diptimayee_Resume-1-1-1.pdf",
      "rawText": "SKILLS LANGUAGES PROJECT DIPTIMAYEE NAYAK SOFTWARE DEVELOPER CONTACT 9777903585 diptimayeen223@gmail.com Sailashree Vihar, Bhubaneswar, Odisha, PIN- 751021 HOBBIES Travelling Dancing Painting Web Development: HTML,CSS, Javascript,React,AngularJs. Programming Language: C,Java. Database: MongoDB,SQL. PROFESSIONAL SUMMARY MASTER OF COMPUTER APPLICATION(MCA)(2022-2024) Trident Accademy Of Creative Techonology,Bhubaneswar. BACHELOR OF SCIENCE(BSC) Odia English Hindi INTERESTS Cooking Gardening Creative activities Handicraft CERTIFICATION Management Information System. Introduction to industry 4.0. Intellectual property. Internship certificate from JavaCEnterpriser Pvt.Ltd PROTTTGRAMMING GUAGE: C,JA EDUCATION Database: MongoDB,SQL. SS Session:2022-2024 INTERMEDIATE Credential college of commerce and science,Bhadrak Session:2016-2018 MATRICULATION Soso Govt Girls High School,soso Highly motivated and dynamic professional seeking a challenging position in the techonology industry when i can leverage my knowledge of emerging techonologies. HEART DISEASE PREDICTION SYSTEM DECLARATION I hereby declare that all the details mentioned above are in accordance with the truth and fact as per my knowledge and i hold the responsibility for the correctness of the above-mentioned particulars. Built a heart disease prediction system by analysing patient data to predict the likelihood of heart disease based on various health metrics. Techonology used:Python Agarapara College,Agarapara(Fakir Mohan University,Balasore"
    },
    "source": "resume",
    "confidence": 86,
    "processingTime": 0
  }
}