{
  "filename": "e819c095-98ac-447b-af3f-156fe219b163.pdf",
  "timestamp": "2025-09-18T10:36:53.471Z",
  "processingTime": 6945,
  "confidence": 66,
  "rawText": "\n\nOBJECTIVE \ngrowth of the organization. \nSeeking a position in a company \nwhere I can make the best of my \npotential and build a valuable skill \nset and contribute to the overall \nSKILLS \n\" Leadership \n. Problem Solving \n\"Time management \n\" Communication \n-PYTHON(Beginner) \nHTML(Beginner) \nTECHNICAL SKILLS \nCSS( Beginner ) \nTamil \nEnglish \nMARUDHU PANDI SELVAMA \nmarudhul 022@gmail.com \nINFORMATION TECHNOLOGY \nLANGUAGES KNOWN \n\" NSS Volunteer \nCERTIFICATIONs \n* Workshop on investigation \non digital forensics \nEDUCATION \nYEAR \n2020 \n2024 \n2020 \n2018 \nDEGREE \nB.TECH \nINFORMATION \nTECHNOLOGY \nHSC \nSSLC \nINTERNSHIP \n. HTML,CSS.PYTHON \nPROJECTS \nINSTITUTION \n\" PLACEMENT SITE. \nKALASALINGAM ACADEMY \nOF RESEARCH AND \nEDUCATION \n62B Anna Colony,Alaoorani, \nThiruthangal,sivakasi, \nVirudhunagar-626130 \nMuthumari Matric Hr \nSec School \nMuthumari Matric Hr \nSec School \n4916382809254 \n\" DETECTION OF DIABETIC RETINOPATHY \nInplant training at io solution in coimbatore,web development-jewellery \nwwcbsite \nPERCENTAGE \nCreating a web application for checking eye discases. \n7.28( CGPA ) \n\"Both Websites are built using HTML, CSs, and Python: \n51% \nA web portal for a college's training and placement cell can help students with \nplacement in a number of ways \n61% ",
  "extractedData": {
    "name": "MARUDHU PANDI SELVAMA",
    "email": "marudhul022@gmail.com",
    "phone": null,
    "linkedinUrl": null,
    "githubUrl": null,
    "portfolioUrl": null,
    "location": "62B Anna Colony, Alaoorani, Thiruthangal, Sivakasi, Virudhunagar-626130",
    "title": null,
    "summary": "Seeking a position in a company where I can make the best of my potential and build a valuable skill set and contribute to the overall growth of the organization.",
    "experience": [],
    "education": [
      {
        "degree": "B.TECH",
        "field": "INFORMATION TECHNOLOGY",
        "university": "KALASALINGAM ACADEMY OF RESEARCH AND EDUCATION",
        "year": "2024",
        "percentage": null,
        "gpa": "7.28",
        "location": "62B Anna Colony, Alaoorani, Thiruthangal, Sivakasi, Virudhunagar-626130"
      },
      {
        "degree": "HSC",
        "field": null,
        "university": "Muthumari Matric Hr Sec School",
        "year": "2020",
        "percentage": "61%",
        "gpa": null,
        "location": null
      },
      {
        "degree": "SSLC",
        "field": null,
        "university": "Muthumari Matric Hr Sec School",
        "year": "2018",
        "percentage": "51%",
        "gpa": null,
        "location": null
      }
    ],
    "projects": [
      {
        "name": "DETECTION OF DIABETIC RETINOPATHY",
        "description": "Creating a web application for checking eye diseases.",
        "techUsed": [
          "HTML",
          "CSS",
          "Python"
        ],
        "duration": null,
        "url": null,
        "achievements": []
      },
      {
        "name": "Web development - jewellery website",
        "description": "Inplant training at io solution in Coimbatore.",
        "techUsed": [
          "HTML",
          "CSS",
          "Python"
        ],
        "duration": null,
        "url": null,
        "achievements": []
      },
      {
        "name": "A web portal for a college's training and placement cell",
        "description": "Helps students with placement in a number of ways.",
        "techUsed": [
          "HTML",
          "CSS",
          "Python"
        ],
        "duration": null,
        "url": null,
        "achievements": []
      }
    ],
    "achievements": [],
    "certifications": [
      {
        "name": "Workshop on investigation on digital forensics",
        "issuer": null,
        "date": null,
        "expiryDate": null,
        "credentialId": null,
        "url": null
      }
    ],
    "skills": [
      "Leadership",
      "Problem Solving",
      "Time management",
      "Communication",
      "PYTHON(Beginner)",
      "HTML(Beginner)",
      "CSS(Beginner)"
    ],
    "interests": [],
    "languages": [
      "Tamil",
      "English"
    ],
    "salary": null,
    "availability": null,
    "remotePreference": null,
    "visaStatus": null,
    "originalData": {
      "filename": "e819c095-98ac-447b-af3f-156fe219b163.pdf",
      "rawText": "OBJECTIVE growth of the organization. Seeking a position in a company where I can make the best of my potential and build a valuable skill set and contribute to the overall SKILLS \" Leadership . Problem Solving \"Time management \" Communication -PYTHON(Beginner) HTML(Beginner) TECHNICAL SKILLS CSS( Beginner ) Tamil English MARUDHU PANDI SELVAMA marudhul 022@gmail.com INFORMATION TECHNOLOGY LANGUAGES KNOWN \" NSS Volunteer CERTIFICATIONs * Workshop on investigation on digital forensics EDUCATION YEAR 2020 2024 2020 2018 DEGREE B.TECH INFORMATION TECHNOLOGY HSC SSLC INTERNSHIP . HTML,CSS.PYTHON PROJECTS INSTITUTION \" PLACEMENT SITE. KALASALINGAM ACADEMY OF RESEARCH AND EDUCATION 62B Anna Colony,Alaoorani, Thiruthangal,sivakasi, Virudhunagar-626130 Muthumari Matric Hr Sec School Muthumari Matric Hr Sec School 4916382809254 \" DETECTION OF DIABETIC RETINOPATHY Inplant training at io solution in coimbatore,web development-jewellery wwcbsite PERCENTAGE Creating a web application for checking eye discases. 7.28( CGPA ) \"Both Websites are built using HTML, CSs, and Python: 51% A web portal for a college's training and placement cell can help students with placement in a number of ways 61%"
    },
    "source": "resume",
    "confidence": 66,
    "processingTime": 0
  }
}