{
  "filename": "f44c2682-b959-4a19-ae94-61c169b73157.pdf",
  "timestamp": "2025-09-29T09:31:42.802Z",
  "processingTime": 3261,
  "confidence": 82,
  "rawText": "\n\nEducation\n8825816433\nContact\npjayakanthan17@gmail.com\n3/317 Duraisamy nagar,kallavi,\nuthangarai(tk),krishnagiri-635304\nAddress\nJAYAKANTHAN\nphp/laravel developer\nI  am  a  skilled  PHP  developer  with  1.3  years  of  experience  in  building  web  applications  and\nwebsites. My expertise includes both front-end and back-end development, allowing me to create\nfull-stack solutions that meet clients' needs. I am passionate about writing clean and efficient code,\nsolving complex problems, and staying up-to-date with the latest web development trends. I am\neager to contribute my skills and knowledge to dynamic and innovative projects.\nExperience\n2021 \n06 JULY'2020 - 28 MARCH'2021\nProjects\nSri Bala Vidhya Matric Hr Sec school\nPercentage : 76.25%\nHSC  \n2017-2021\n2016-2017\nCss\nlaravel Framework\nJavascript(jquery,\najax)\nHtml 5\nPhp\nBootstrap\nEnglish\nTamil\nKannada(under\nstanding)\nExpertise\nLanguage\nSri bala vidhya matric higher secondary\nschool\nPercentage : 83%\nMysql\nhttps://www.linkedin.com/in/jayakant\nhan-p-3b724a22b/\nSSLC\nSkills\nDeveloped and maintained web applications using PHP and Laravel \nDeveloped  and  maintained  database  schemas,  ensuring  data  integrity  and\nefficiency.\nDesigned and optimized MySQL databases, improving data retrieval efficiency\nand ensuring data integrity.\nCollaborated with front-end developers to create seamless user experiences and\nresponsive designs.\nImplemented security measures to protect web applications against common\nvulnerabilities.\nAssisted in troubleshooting and resolving technical issues for clients.\nTesting  and  debugging  and  troubleshooting  to  identify  and  resolve  issues\npromptly.\nVeltech University Chennai\nWORKING EXPERIENCE\nSKILLS\nHTML\nCSS\nJavaScript   [Ajax & Jquery]\nBootstrap\nFront-end Technologies:-\nBack-end Technologies:-\nPhp\nLaravel Framework\nDatabases:-\nMySQL server\nLaravel Framework\nWeb Development Tools: Visual Studio Code,Sublime\nAPI Integration - Web Security Best Practices\nPerformance Optimization - Responsive Web Design\nGs Elevetors\nElevator Installation and Modernization \nPreventive Maintenance \nTroubleshooting and Diagnostics\nTroubleshooting and Diagnostics\nWeb Application Development\nStock Management\nEmployee Leave ManagementSystem \nSimple Login and Registration Project \nPaypal Payment Gateway Integration\nTamilnadu college of Engineering\n(B.E)Mechanical Engineering",
  "extractedData": {
    "name": "JAYAKANTHAN",
    "email": "pjayakanthan17@gmail.com",
    "phone": "8825816433",
    "linkedinUrl": "https://www.linkedin.com/in/jayakanthan-p-3b724a22b/",
    "githubUrl": null,
    "portfolioUrl": "https://code-projects.org/employee-leave-management-site-using-php-source-code/",
    "location": "3/317 Duraisamy nagar, kallavi, uthangarai(tk), krishnagiri-635304",
    "title": "php/laravel developer",
    "summary": "I am a skilled PHP developer with 1.3 years of experience in building web applications and websites. My expertise includes both front-end and back-end development, allowing me to create full-stack solutions that meet clients' needs. I am passionate about writing clean and efficient code, solving complex problems, and staying up-to-date with the latest web development trends. I am eager to contribute my skills and knowledge to dynamic and innovative projects.",
    "experience": [],
    "education": [
      {
        "degree": "HSC",
        "field": null,
        "university": "Sri Bala Vidhya Matric Hr Sec school",
        "year": "2016-2017",
        "percentage": "76.25%",
        "gpa": null,
        "location": null
      },
      {
        "degree": "SSLC",
        "field": null,
        "university": "Sri bala vidhya matric higher secondary school",
        "year": null,
        "percentage": "83%",
        "gpa": null,
        "location": null
      },
      {
        "degree": "B.E",
        "field": "Mechanical Engineering",
        "university": "Tamilnadu college of Engineering",
        "year": null,
        "percentage": null,
        "gpa": null,
        "location": null
      }
    ],
    "projects": [],
    "achievements": [],
    "certifications": [],
    "skills": [
      "HTML",
      "CSS",
      "JavaScript",
      "Ajax",
      "Jquery",
      "Bootstrap",
      "Php",
      "Laravel Framework",
      "MySQL",
      "Visual Studio Code",
      "Sublime",
      "API Integration",
      "Web Security Best Practices",
      "Performance Optimization",
      "Responsive Web Design"
    ],
    "interests": [],
    "languages": [
      "English",
      "Tamil",
      "Kannada"
    ],
    "salary": null,
    "availability": null,
    "remotePreference": null,
    "visaStatus": null,
    "originalData": {
      "filename": "f44c2682-b959-4a19-ae94-61c169b73157.pdf",
      "rawText": "Education 8825816433 Contact pjayakanthan17@gmail.com 3/317 Duraisamy nagar,kallavi, uthangarai(tk),krishnagiri-635304 Address JAYAKANTHAN php/laravel developer I am a skilled PHP developer with 1.3 years of experience in building web applications and websites. My expertise includes both front-end and back-end development, allowing me to create full-stack solutions that meet clients' needs. I am passionate about writing clean and efficient code, solving complex problems, and staying up-to-date with the latest web development trends. I am eager to contribute my skills and knowledge to dynamic and innovative projects. Experience 2021 06 JULY'2020 - 28 MARCH'2021 Projects Sri Bala Vidhya Matric Hr Sec school Percentage : 76.25% HSC 2017-2021 2016-2017 Css laravel Framework Javascript(jquery, ajax) Html 5 Php Bootstrap English Tamil Kannada(under standing) Expertise Language Sri bala vidhya matric higher secondary school Percentage : 83% Mysql https://www.linkedin.com/in/jayakant han-p-3b724a22b/ SSLC Skills Developed and maintained web applications using PHP and Laravel Developed and maintained database schemas, ensuring data integrity and efficiency. Designed and optimized MySQL databases, improving data retrieval efficiency and ensuring data integrity. Collaborated with front-end developers to create seamless user experiences and responsive designs. Implemented security measures to protect web applications against common vulnerabilities. Assisted in troubleshooting and resolving technical issues for clients. Testing and debugging and troubleshooting to identify and resolve issues promptly. Veltech University Chennai WORKING EXPERIENCE SKILLS HTML CSS JavaScript [Ajax & Jquery] Bootstrap Front-end Technologies:- Back-end Technologies:- Php Laravel Framework Databases:- MySQL server Laravel Framework Web Development Tools: Visual Studio Code,Sublime API Integration - Web Security Best Practices Performance Optimization - Responsive Web Design Gs Elevetors Elevator Inst"
    },
    "source": "resume",
    "confidence": 82,
    "processingTime": 0
  }
}