{
  "filename": "Maria Antoniraj_.Net Lead_Tenjumps.pdf",
  "timestamp": "2025-09-03T17:21:47.406Z",
  "processingTime": 79814,
  "confidence": 98,
  "rawText": "\n\n    Maria Antoniraj  \nSenior Dotnet Developer  \nantoni651@gmail.com | +971502669478 | https://www.linkedin.com/in/antoniraj-antoniraj-1a595a63/ \nAl Karama, Dubai, United Arab Emirates  \nSUMMARY \n \n❖ 8.6 Years of experience in the Requirements Gathering, analysis, design, and development of \nweb applications and database design, Deployment and supporting using Microsoft \nTechnologies. \n❖ I am having good exposure on different domain like Insurance, Finance, Mutual Fund, \nCommercial, HRMS, and Healthcare projects for leading provider organizations. \n❖ Good in Microsoft Visual Studio IDE using ASP.NET, C#, MVC 5.0, .Net Core, Web API, WCF, \nORM  (ADO,  EF),  Microservices,  SQL,  PL/SQL,  OOPS,  SOLID  Principle,  Design  Pattern,  AJAX, \nJavaScript, jQuery, HTML, CSS, Azure, git, LINQ, Angular \n❖ I  hold  a  good  knowledge  of  all  the  phases  of  software  Development  Life  Cycle  (SDLC)  and \npossesses exceptional analytical and problem – solving  skills and a good team player with \nexcellent interpersonal and communication skills. \n❖ I  have  completed  my  Bachelor  of  Computer  Science  and  Master  of  Computer  Application  from \nIndia. \nProfessional Experience \n \nOrganization Designation Duration \nCitiusTech Healthcare Technology \nPvt Ltd \nTechnical Lead II Sep 2024 to Feb 2025 \nWipro Limited \nSenior Project Engineer \nOct 2019 to Nov 2023 \nFuture Focus Infotech Pvt Ltd \n(Client TCS) \n.Net Developer Apr 2018 to Dec 2018 \nJOULESTOWATTS BUSINESS \nSOLUTIONS pvt ltd (Client \nCapgemini) \nDotnet Developer Sep 2017 to March 2018 \nSterling Software pvt ltd Software Engineer Feb 2016 to Aug 2017 \nHesperus Infosys Junior Dotnet Developer Oct 2014 to Oct 2015 \n\nEducational Qualification \n \n \nPeriod Course \nCollege/School \n \nPercentage \n \n2010 - 2013 \nM.C.A \nDepartment of Computer Science, \nSt.Joseph’s College (Autonomous), \nBharathidasan University, Trichy, India \n77.8 % \n2007 - 2010 B. Sc – Computer Science \nDepartment of Computer science, \nSacred Heart College, Tirupattur, Vellore, India \n67 % \n2007 Higher Secondary Course, \nSacred Heart Hi. Secondary School, Iruppukurichy, \nVirudhachalam, India \n63 % \n2005 S. S. L. C. \nSacred Heart Hi. Secondary School, Iruppukurichy, \nVirudhachalam, India \n79.8 % \n \n    Technical Skills \n \nSkills \nProgramming Languages C#, SQL, C \nScripting Languages JavaScript, HTML, XML, CSS, jQuery, Ajax, Angular \nWeb Server IIS, Kestrel \nDatabase Microsoft SQL Server 2008. Oracle 11 \nFrame Work ASP.NET Web Form, ASP.NET MVC5. .Net Core, WEB API, WCF, ADO.NET, \nENTITY FRAMWORK, Microservices \nTools MRT, Crystal Report \nIDE Visual Studio 2013, 2012. 2015, 2017, 2019 \nConfiguration Management \nTool \nTFS, GIT, VSTS, MICROSOFT Azure \n \n \nCertifications: \n1. ASP.NET, Institute - Shalom Infotech, Location – Trichy, Year 2012 \n2. Azure Developer Associate, Institute – Microsoft, Year 2025 \n3. Hardware, Institute – Systech, Location -Trichy, Year 2011 \n4. Typewriting English, Department of Technical Education, Tamil Nadu, Year 2011 \n \n \n \n \n \n \n \n \n \n \n\nProjects Summary \n1. General Electric (GE) – Radiology \n2. Loreal India  \n3. Project Management Information System (PMIS) for AVEVA Global Services – Project Space \n4. Charles Schwab \n5. Tata Aviva \n6. MOSS AP \n7. CAMSOnline \n8. Insunet \n9. HRMS \n10. PHIS Online \n \nCompany: CitiusTech Healthcare Technology Pvt Ltd \n \nTitle  Project: General Electric (GE) - Radiology, Location: Bangalore – India, \n Duration: Sep 2024 - Feb 2025 \nDescription \nGE HealthCare provides clinicians with innovative imaging solutions and \npharmaceutical diagnostic imaging agents for their radiology departments, \nincluding Computed Tomography, Magnetic Resonance Imaging, Ultrasound, \nMolecular Imaging, X-Ray, Mammography, CT scan, MRI, Interventional Image \nGuided Systems, Surgical Imaging and Radiology IT. \nOur intelligent products and solutions help achieve faster, easier exam \nworkflows, improved clinical outcomes and drive efficient imaging operations..  \nTeam Size 8 \nTechnologies \n.Net Core, C#, Web API, WCF, jQuery, Ajax, GIT, Web Application, CSS, LINQ, \nbootstrap, SQL, Stored Procedure, Views, Microsoft Azure Cloud, Entity \nFramework, Design Pattern, microservices, unit testing, Angular \nRoles and Responsibility \nDone some security-based enhancement and changes, Developed Finacle API, \nand buck fixing tasks,  \nDeveloped and tested different cases \nBack-end coding of Application and hardware setup \nMaintained code versions on GitHub \nDeveloped and integrated API, identified bugs and provided solution \nDeployed changes to git repository by DevOps \n \nCompany: WIPRO LTD \nTitle  Project: Loreal India, Location: Mumbai – India, \n Duration - Aug 2023 - Nov 2023 \nDescription \n“LEAP Portal” is a web portal accessed by trainers of all divisions for education \nreporting, Scheduling calendar Record education activities like Booking \nparticipants Mark Attendance Evaluation Stock Utilization Manual \nupdate/uploaded from DART or free Issue tracker Leap Closing.  \n“Leap app” is a mobile tool used to register hairdressers and salons to LEAP. \nAlso, trainers can report education activities using Classroom Module. It’s for \nSales and Trainer. Another five websites Lucky Draw, MLJ Application, Staffs \nSales Application, The store Application, TNA_Application. SalesPortal for \nFinancial Activities. \nTeam Size 2 \nTechnologies \nASP.NET Webforms, ASP.NET MVC, C#, Web API, WCF, Windows Schedular, \njQuery, Ajax, GIT, CSS, LINQ, bootstrap, SQL, Stored Procedure, Views, \nMicrosoft Azure Cloud, ADO.NET, microservices, Angular \n\nRoles and Responsibility \nDeveloped and tested different cases \nBack-end coding of Application and hardware setup \nMaintained code versions on GitHub \nDeveloped and integrated API, identified bugs and provided solution \nDeployed changes to git repository by DevOps \n \nCompany: WIPRO LTD \n \nTitle Project: Project Management Information System (PMIS) for AVEVA \nGlobal, Location: Bangalore – India, Duration:  July 2020 - July 2023 \nDescription \nProjectspace is an AVEVA internal web application which serves as the Project \nManagement Information System (PMIS) for AVEVA Global Services. \nProjectspace receives and displays financial data from AVEVA’s Oracle, and \nProjectspace allows project managers to enter project status data (referred to \nas non-financial data). The combination of financial and non-financial data \npresented in Projectspace creates a complete status overview for all Global \nServices projects. The status overview allows project managers and other \nmanagers to properly monitor and control Global Service projects. \nProjectspace (Web Application), Projectspace Batch job (Daily and monthly task \nschedular), CSAT (Customer survey Web Application), CSAT Survey Service \n(Survey Initiate Request Service), CSAT Response Service (Survey Response \ncapture Web Service) \nTeam Size 3 \nTechnologies \n.Net MVC5, C#, Web API, WCF, jQuery, Unobtrusive Validation, GIT, \nMicroservices, CSS, bootstrap, LINQ, SQL, Oracle pl/SQL, Stored Procedure, \nViews, Microsoft Azure Cloud, Entity Framework, Design Pattern \nRoles and Responsibility \nGathering requirements and understanding the client needs \nDeveloped modules, resolved bugs and kept on time support \nMonitor and track entire application with daily basis \nWritten testcase for functions, debug and troubleshoot the issues \nWorked in offshore development and supported onsite tasks \nSupported with onsite people parallelly to develop business dashboard \nDocumented for Artifact, project flow diagram and created requirements \ndocument, also the test case and use case documents, Documented API Details \nDeployed to Azure cloud using git \n \nCompany: WIPRO LTD \n \nTitle Project: Charles Schwab, Location: Bangalore – India,  \nDuration: Dec 2019 - June 2020 \nDescription \nRWT –Retail Web Technologies is Web application using in Charles Schwab \nInvestment Management. \nTeam Size 4 \nTechnologies .Net core, Web API, Angular 8, jQuery, Unobtrusive Validation, Test Driven \nDevelopment- Nunit, Moq, Agile Methodologies, Jira- Tracking Development \nProcess, Stash- Maintaining Repositories, GIT, VSTS, MICROSOFT AZURE Cloud, \nMicroservices, Entity Framework, Design Pattern, LINQ, unit testing, Angular \nRoles and Responsibility \nWorked sprint story with Agile team \nIdentified bugs, troubleshoot the issues \nDone query changes and written stored procedure in RWT Database \nWorked for environment setup and maintained documents \nGathering requirements and understanding the client needs \nProvide KT and train the new resource \n \n \n     \n \n\nCompany: Future Focus Infotech Pvt Ltd \n \nTitle \nProject: AVIVA, Location: Bangalore – India, Duration: Apr2018 - Dec2018 \n \nDescription \nAVIVA are the largest general insurer and a leading life and pensions provider \nand they have a strong international presence in Europe, Canada and Asia. \nAviva offer a wide range of insurance and savings products to help people \nprotect what’s important to them and save for a comfortable future. Aviva \nCustomer portal is a Hub and there are many micro applications My Policy, My \nPension, My Documents, My Motor, My Home, My Profile, My Claim, My \nPayments, My Health, Esecurity, and etc. \nTeam Size 8 \nTechnologies \nC# MVC, .Netcore, Web API, Entity Framework, StructureMap DI, jQuery \nMicroservices, Test Driven Development- Nunit, Moq, Agile Methodologies, \nJira- Tracking Development Process, Stash- Maintaining Repositories, GIT, \nVSTS, MICROSOFT AZURE Cloud, Design Pattern, unit testing \nRoles and Responsibility \nFollowed agile based work mode with Scrum master \nWorked story task in every sprint \nMentoring team members to understand the AVIVA Application \nProvided KT and trained new resources \nDone test driven development and reviewed for quality code \nConnected with different team members in distributed application \n  \nCompany: Joulestowatts Business Solutions Pvt Ltd \n \nTitle \nProject: MOSS AP, Location: Chennai – India, Duration: Sep2017 - March 2018 \nDescription \nMOSS “Merchant Operations Support System” is used by ASIA-PACIFIC users \n(Sales Person) to onboard merchant’s contract information through MOSS AP \nUI. The merchant information was closely scrutinized by the Global payments \nteams in different stages and processed for further approvals. The on boarding \nof the merchant follows the workflow and the information is passed to \ndifferent downstream system. \nTeam Size 5 \nTechnologies ASP.NET MVC, C#, Web Service, Web Application, WEB API, CSS, XML, SQL, \nStored Procedure, Microsoft Azure cloud, git, microservices. \nRoles and Responsibility \nHad support role in that dedicated team \nDocument preparation and database changes \nMonitoring the entire application everyday \nWritten API function \nConcentrated application performance, memory management and application \nsecurity \nCompany: Sterling Software Pvt Ltd \n \nTitle  Project: CAMSOnline, Location: Chennai – India, Duration 2016 - Aug 2017 \nDescription CAMSOnline is the Mutual Fund and NSE Website used by CAMS Organization. \nThe main objective of this website is to handle all the purchase and sales order \ntransactions of Mutual Fund and to generate the statistical reports. \nTeam Size 5 \nTechnologies \nASP.NET Web Form, C#, Web Service, CSS, Java Script, MRT Report, Crystal \nReport, Stored Procedure, SQL, IIS, WCF, git, unit testing \n\nRoles and Responsibility Developed Mutual Fund application in the Scratch level \nTrained bellowed team members to understand the client requirements \nDeveloped database design – Written stored procedure, function, view and \ntrigger \nHave attended lot of training for Mutual Fund domain conducted by CAMS \nDeveloped web services \nDesigned MRT Tool for report generation \nDeployed changes to IIS Server \n \nCompany: Sterling Software Pvt Ltd \n \nTitle  Project: Insunet, Location: Chennai – India, Duration: Feb2016 - Aug2017 \nDescription \nInsunet is Life, Health and Motor Insurance Management application. This \napplication acts as a platform to maintain all their business activities under one \nroof from various places in and around the globe. \nThrough this site the policy holder can join for various policies and then they \ncan follow entire process of Insurance. \nTeam Size 4 \nTechnologies ASP.NET Web Forms, C#, ADO.NET, CSS, Java Script, AJAX, Stored Procedure, \nSQL, IIS, windows server, MRT Report, Crystal Report, WCF, Web Service, \nmicroservices, unit testing. \nRoles and Responsibility Developed Mutual Fund application in the Scratch level \nTrained bellowed team members to understand the client requirements \n \n \nDeveloped database design – Written stored procedure, function, view and \ntrigger \nHave attended lot of training for Mutual Fund domain conducted by CAMS \nDeveloped web services \nDesigned MRT Tool for report generation \nDeployed changes to IIS Server \nCompany: Hesperus Infosys \n \nTitle Project: HRMS - Human Resource Management System, Location: Chennai \n– India, Duration: Oct 2014 - Oct 2015 \nDescription \nThis project titled “Human Resource Management System” is considered as \nManagement application. Main purpose of this application maintained the \ndata about Company or College Employees, Students every day follow-ups, \nScheme Calculation, and payment details. This application acts as a platform to \nmaintain all their branches activities under one roof from various places in and \naround the globe. \nFinally, the reports will be generated by this system based on branch wise and \ncompany wise (ex: Daily, Monthly, and yearly etc...) \nThe Modules about Time and Attendance, Payroll System, Recruitment Process, \nPerformance and Appraisal, Career and Development. \nTeam Size 4 \nTechnologies \nASP.NET Web Form, C#, CSS, ADO.NET, Java Script, AJAX, SQL Server2008, \nStored Procedure, Crystal Reports, IIS, \nRoles and Responsibility \nDeveloped entire application with scratch level \nDeveloped complete database design \nVisited client place to understand the business process and product \nMonitoring the application for daily basis \nConcentrated application performance, memory management and application \nsecurity \nTaken care of application deployment and server performance \n \n    \n \n\n Internship: JJS \n \nTitle PHIS Online (Public Health Information System), Location: Chennai – India, \nDescription \nA Web Application developed for a health organization. The purpose of \nthe project is collecting the health data from the Public and Schools \nin various divisions and generates various types of reports (Monthly \nand yearly). \nTeam Size 4 \nTechnologies ASP.NET MVC, MS-SQL, IIS, \nRoles and Responsibility Developed some modules in the Public Health Information System \nIt was college Internship project \n \n \n \nPermanent Address: \nNO. 165, South Street, Gandhi Nagar, Iruppukurichi, Virudhachalam, Tamil Nadu, India -607804 \nMobile: +91 9108152578 ",
  "extractedData": {
    "name": "Maria Antoniraj",
    "email": "antoni651@gmail.com",
    "phone": "+971502669478",
    "linkedinUrl": "https://www.linkedin.com/in/antoniraj-antoniraj-1a595a63/",
    "githubUrl": null,
    "portfolioUrl": null,
    "location": "Al Karama, Dubai, United Arab Emirates",
    "title": "Senior Dotnet Developer",
    "summary": "8.6 Years of experience in the Requirements Gathering, analysis, design, and development of web applications and database design, Deployment and supporting using Microsoft Technologies. I am having good exposure on different domain like Insurance, Finance, Mutual Fund, Commercial, HRMS, and Healthcare projects for leading provider organizations. Good in Microsoft Visual Studio IDE using ASP.NET, C#, MVC 5.0, .Net Core, Web API, WCF, ORM (ADO, EF), Microservices, SQL, PL/SQL, OOPS, SOLID Principle, Design Pattern, AJAX, JavaScript, jQuery, HTML, CSS, Azure, git, LINQ, Angular. I hold a good knowledge of all the phases of software Development Life Cycle (SDLC) and possesses exceptional analytical and problem-solving skills and a good team player with excellent interpersonal and communication skills. I have completed my Bachelor of Computer Science and Master of Computer Application from India.",
    "experience": [
      {
        "jobTitle": "Technical Lead II",
        "company": "CitiusTech Healthcare Technology Pvt Ltd",
        "duration": "Sep 2024 - Feb 2025",
        "startDate": "2024-09",
        "endDate": "2025-02",
        "techUsed": [
          ".Net Core",
          "C#",
          "Web API",
          "WCF",
          "jQuery",
          "Ajax",
          "GIT",
          "Web Application",
          "CSS",
          "LINQ",
          "bootstrap",
          "SQL",
          "Stored Procedure",
          "Views",
          "Microsoft Azure Cloud",
          "Entity Framework",
          "Design Pattern",
          "microservices",
          "unit testing",
          "Angular"
        ],
        "description": "GE HealthCare provides clinicians with innovative imaging solutions and pharmaceutical diagnostic imaging agents for their radiology departments.",
        "achievements": [
          "Done some security-based enhancement and changes",
          "Developed Finacle API",
          "Developed and tested different cases",
          "Back-end coding of Application and hardware setup",
          "Maintained code versions on GitHub",
          "Developed and integrated API",
          "Deployed changes to git repository by DevOps"
        ]
      },
      {
        "jobTitle": "Senior Project Engineer",
        "company": "Wipro Limited",
        "duration": "Oct 2019 - Nov 2023",
        "startDate": "2019-10",
        "endDate": "2023-11",
        "techUsed": [
          "ASP.NET Webforms",
          "ASP.NET MVC",
          "C#",
          "Web API",
          "WCF",
          "Windows Schedular",
          "jQuery",
          "Ajax",
          "GIT",
          "CSS",
          "LINQ",
          "bootstrap",
          "SQL",
          "Stored Procedure",
          "Views",
          "Microsoft Azure Cloud",
          "ADO.NET",
          "microservices",
          "Angular"
        ],
        "description": "Worked on various projects including LEAP Portal and Project Management Information System (PMIS) for AVEVA Global.",
        "achievements": [
          "Developed and tested different cases",
          "Back-end coding of Application and hardware setup",
          "Maintained code versions on GitHub",
          "Developed and integrated API",
          "Deployed changes to git repository by DevOps"
        ]
      },
      {
        "jobTitle": ".Net Developer",
        "company": "Future Focus Infotech Pvt Ltd (Client TCS)",
        "duration": "Apr 2018 - Dec 2018",
        "startDate": "2018-04",
        "endDate": "2018-12",
        "techUsed": [
          "C# MVC",
          ".Netcore",
          "Web API",
          "Entity Framework",
          "StructureMap DI",
          "jQuery",
          "Microservices",
          "Test Driven Development- Nunit",
          "Moq",
          "Agile Methodologies",
          "Jira",
          "Stash",
          "GIT",
          "VSTS",
          "MICROSOFT AZURE Cloud",
          "Design Pattern",
          "unit testing"
        ],
        "description": "Worked on AVIVA Customer portal, a Hub with many micro applications.",
        "achievements": [
          "Followed agile based work mode with Scrum master",
          "Worked story task in every sprint",
          "Mentoring team members",
          "Provided KT and trained new resources",
          "Done test driven development and reviewed for quality code"
        ]
      },
      {
        "jobTitle": "Dotnet Developer",
        "company": "JOULESTOWATTS BUSINESS SOLUTIONS pvt ltd (Client Capgemini)",
        "duration": "Sep 2017 - March 2018",
        "startDate": "2017-09",
        "endDate": "2018-03",
        "techUsed": [
          "ASP.NET MVC",
          "C#",
          "Web Service",
          "Web Application",
          "WEB API",
          "CSS",
          "XML",
          "SQL",
          "Stored Procedure",
          "Microsoft Azure cloud",
          "git",
          "microservices"
        ],
        "description": "Worked on MOSS 'Merchant Operations Support System'.",
        "achievements": [
          "Had support role in that dedicated team",
          "Document preparation and database changes",
          "Monitoring the entire application everyday",
          "Written API function",
          "Concentrated application performance, memory management and application security"
        ]
      },
      {
        "jobTitle": "Software Engineer",
        "company": "Sterling Software pvt ltd",
        "duration": "Feb 2016 - Aug 2017",
        "startDate": "2016-02",
        "endDate": "2017-08",
        "techUsed": [
          "ASP.NET Web Form",
          "C#",
          "Web Service",
          "CSS",
          "Java Script",
          "MRT Report",
          "Crystal Report",
          "Stored Procedure",
          "SQL",
          "IIS",
          "WCF",
          "git",
          "unit testing"
        ],
        "description": "Worked on CAMSOnline and Insunet projects.",
        "achievements": [
          "Developed Mutual Fund application in the Scratch level",
          "Trained bellowed team members",
          "Developed database design",
          "Developed web services",
          "Designed MRT Tool for report generation",
          "Deployed changes to IIS Server"
        ]
      },
      {
        "jobTitle": "Junior Dotnet Developer",
        "company": "Hesperus Infosys",
        "duration": "Oct 2014 - Oct 2015",
        "startDate": "2014-10",
        "endDate": "2015-10",
        "techUsed": [
          "ASP.NET Web Form",
          "C#",
          "CSS",
          "ADO.NET",
          "Java Script",
          "AJAX",
          "SQL Server2008",
          "Stored Procedure",
          "Crystal Reports",
          "IIS"
        ],
        "description": "Worked on HRMS - Human Resource Management System.",
        "achievements": [
          "Developed entire application with scratch level",
          "Developed complete database design",
          "Visited client place to understand the business process",
          "Monitoring the application for daily basis",
          "Concentrated application performance",
          "Taken care of application deployment and server performance"
        ]
      }
    ],
    "education": [
      {
        "degree": "M.C.A",
        "field": "Computer Science",
        "university": "St.Joseph’s College (Autonomous), Bharathidasan University",
        "year": "2013",
        "percentage": "77.8%",
        "gpa": null,
        "location": "Trichy, India"
      },
      {
        "degree": "B. Sc",
        "field": "Computer Science",
        "university": "Sacred Heart College",
        "year": "2010",
        "percentage": "67%",
        "gpa": null,
        "location": "Tirupattur, Vellore, India"
      }
    ],
    "projects": [
      {
        "name": "General Electric (GE) - Radiology",
        "description": "GE HealthCare provides clinicians with innovative imaging solutions and pharmaceutical diagnostic imaging agents for their radiology departments.",
        "techUsed": [
          ".Net Core",
          "C#",
          "Web API",
          "WCF",
          "jQuery",
          "Ajax",
          "GIT",
          "Web Application",
          "CSS",
          "LINQ",
          "bootstrap",
          "SQL",
          "Stored Procedure",
          "Views",
          "Microsoft Azure Cloud",
          "Entity Framework",
          "Design Pattern",
          "microservices",
          "unit testing",
          "Angular"
        ],
        "duration": "Sep 2024 - Feb 2025",
        "url": null,
        "achievements": [
          "Done some security-based enhancement and changes",
          "Developed Finacle API",
          "Developed and tested different cases",
          "Back-end coding of Application and hardware setup",
          "Maintained code versions on GitHub",
          "Developed and integrated API",
          "Deployed changes to git repository by DevOps"
        ]
      },
      {
        "name": "Loreal India",
        "description": "LEAP Portal is a web portal accessed by trainers of all divisions for education reporting, Scheduling calendar Record education activities.",
        "techUsed": [
          "ASP.NET Webforms",
          "ASP.NET MVC",
          "C#",
          "Web API",
          "WCF",
          "Windows Schedular",
          "jQuery",
          "Ajax",
          "GIT",
          "CSS",
          "LINQ",
          "bootstrap",
          "SQL",
          "Stored Procedure",
          "Views",
          "Microsoft Azure Cloud",
          "ADO.NET",
          "microservices",
          "Angular"
        ],
        "duration": "Aug 2023 - Nov 2023",
        "url": null,
        "achievements": [
          "Developed and tested different cases",
          "Back-end coding of Application and hardware setup",
          "Maintained code versions on GitHub",
          "Developed and integrated API",
          "Deployed changes to git repository by DevOps"
        ]
      }
    ],
    "achievements": [],
    "certifications": [
      {
        "name": "ASP.NET",
        "issuer": "Shalom Infotech",
        "date": "2012",
        "expiryDate": null,
        "credentialId": null,
        "url": null
      },
      {
        "name": "Azure Developer Associate",
        "issuer": "Microsoft",
        "date": "2025",
        "expiryDate": null,
        "credentialId": null,
        "url": null
      },
      {
        "name": "Hardware",
        "issuer": "Systech",
        "date": "2011",
        "expiryDate": null,
        "credentialId": null,
        "url": null
      },
      {
        "name": "Typewriting English",
        "issuer": "Department of Technical Education, Tamil Nadu",
        "date": "2011",
        "expiryDate": null,
        "credentialId": null,
        "url": null
      }
    ],
    "skills": [
      "C#",
      "SQL",
      "C",
      "JavaScript",
      "HTML",
      "XML",
      "CSS",
      "jQuery",
      "Ajax",
      "Angular",
      "IIS",
      "Kestrel",
      "Microsoft SQL Server 2008",
      "Oracle 11",
      "ASP.NET Web Form",
      "ASP.NET MVC5",
      ".Net Core",
      "WEB API",
      "WCF",
      "ADO.NET",
      "ENTITY FRAMEWORK",
      "Microservices",
      "MRT",
      "Crystal Report",
      "Visual Studio 2013",
      "2012",
      "2015",
      "2017",
      "2019",
      "TFS",
      "GIT",
      "VSTS",
      "MICROSOFT Azure"
    ],
    "interests": [],
    "languages": [],
    "originalData": {
      "filename": "Maria Antoniraj_.Net Lead_Tenjumps.pdf",
      "rawText": "Maria Antoniraj Senior Dotnet Developer antoni651@gmail.com | +971502669478 | https://www.linkedin.com/in/antoniraj-antoniraj-1a595a63/ Al Karama, Dubai, United Arab Emirates SUMMARY ❖ 8.6 Years of experience in the Requirements Gathering, analysis, design, and development of web applications and database design, Deployment and supporting using Microsoft Technologies. ❖ I am having good exposure on different domain like Insurance, Finance, Mutual Fund, Commercial, HRMS, and Healthcare projects for leading provider organizations. ❖ Good in Microsoft Visual Studio IDE using ASP.NET, C#, MVC 5.0, .Net Core, Web API, WCF, ORM (ADO, EF), Microservices, SQL, PL/SQL, OOPS, SOLID Principle, Design Pattern, AJAX, JavaScript, jQuery, HTML, CSS, Azure, git, LINQ, Angular ❖ I hold a good knowledge of all the phases of software Development Life Cycle (SDLC) and possesses exceptional analytical and problem – solving skills and a good team player with excellent interpersonal and communication skills. ❖ I have completed my Bachelor of Computer Science and Master of Computer Application from India. Professional Experience Organization Designation Duration CitiusTech Healthcare Technology Pvt Ltd Technical Lead II Sep 2024 to Feb 2025 Wipro Limited Senior Project Engineer Oct 2019 to Nov 2023 Future Focus Infotech Pvt Ltd (Client TCS) .Net Developer Apr 2018 to Dec 2018 JOULESTOWATTS BUSINESS SOLUTIONS pvt ltd (Client Capgemini) Dotnet Developer Sep 2017 to March 2018 Sterling Software pvt ltd Software Engineer Feb 2016 to Aug 2017 Hesperus Infosys Junior Dotnet Developer Oct 2014 to Oct 2015 Educational Qualification Period Course College/School Percentage 2010 - 2013 M.C.A Department of Computer Science, St.Joseph’s College (Autonomous), Bharathidasan University, Trichy, India 77.8 % 2007 - 2010 B. Sc – Computer Science Department of Computer science, Sacred Heart College, Tirupattur, Vellore, India 67 % 2007 Higher Secondary Course, Sacred Heart Hi. Secondary School, Iruppukurichy"
    },
    "source": "resume",
    "confidence": 98,
    "processingTime": 0
  }
}