{
  "filename": "Pushparani-resume.pdf",
  "timestamp": "2025-09-09T05:46:06.369Z",
  "processingTime": 8678,
  "confidence": 98,
  "rawText": "\n\n \nMobile :  8489235259 \nE-Mail  : pushparanis0905@gmail.com \nGithub : github.com/Pushparani S \nLinkedIn :  linkedin.com/in/pushparani-s-1437b1243 \nPushparani S \nWeb Developer \n \nSUMMARY \n \n \nA motivated individual with in-depth knowledge of languages and development tools, seeking a position in a growth-oriented company \nwhere I can use my skills to the advantage of the company while having the scope to develop my own skills. \n \nTECHNICAL SKILLS \n \n◆ HTML5 ◆ Laravel \n◆ CSS3 ◆ CodeIgniter \n◆ JavaScript ◆ MySQL \n◆ JQuery JS ◆ REST APIs \n◆ PHP ◆ Moodle LMS \n \nWORK EXPERIENCE \n \nCOMPANY: X-MEDIA SOLUTIONS \nROLE: WEB DEVELOPER \nEXPERIENCE : 1 YEAR (September 2022 - PRESENT) \nPROJECTS: \n◆ L&T Workmen Mobilization (web & mobile) - Internal Communication and Worker hiring management App \n \n◆ CDMS Online University (web) - E-Learning Platform \n◆ Avtarlabs (web) - E-learning Platform \n◆ VRBIZTEC (web) - Engineering Drawings - Viewing Application \n◆ Canli (website) - E-commerce Website \n \nROLES & RESPONSIBILITIES : \n \n◆ Design and implement database schemas for web applications. This includes creating tables, columns, and relationships, and ensuring \nthat the schema meets the needs of the application. \n◆ Integrate payment processing into web applications. This includes working with payment processors, configuring the integration, and \ntesting the integration. \n◆ Design and develop REST APIs that meet the needs of clients and users. This includes defining the API's endpoints, parameters, and \nresponses. \n◆ Integrate third-party APIs into web applications. This includes understanding the third-party API's Conducted Functional, Regression, \nIntegration and System testing to identify the software defects. \n \nEDUCATIONAL QUALIFICATIONS \n \nBACHELOR DEGREE : B.Sc(Mathematics) - Manonmaniam Sundarnar University(2017-2020). \nMASTER DEGREE : M.Sc(Mathematics) - Manonmaniam Sundarnar University (2020-2022). \n \nCOURSES \n \nJava (Core Java) : Fita Academy, Chennai. ",
  "extractedData": {
    "name": "Pushparani S",
    "email": "pushparanis0905@gmail.com",
    "phone": "8489235259",
    "linkedinUrl": "linkedin.com/in/pushparani-s-1437b1243",
    "githubUrl": "github.com/Pushparani",
    "portfolioUrl": null,
    "location": null,
    "title": "Web Developer",
    "summary": "A motivated individual with in-depth knowledge of languages and development tools, seeking a position in a growth-oriented company where I can use my skills to the advantage of the company while having the scope to develop my own skills.",
    "experience": [
      {
        "jobTitle": "Web Developer",
        "company": "X-MEDIA SOLUTIONS",
        "duration": "September 2022 - Present",
        "startDate": "2022-09",
        "endDate": "Present",
        "techUsed": [
          "HTML5",
          "Laravel",
          "CSS3",
          "CodeIgniter",
          "JavaScript",
          "MySQL",
          "JQuery JS",
          "REST APIs",
          "PHP",
          "Moodle LMS"
        ],
        "description": "Design and implement database schemas for web applications. Integrate payment processing into web applications. Design and develop REST APIs. Integrate third-party APIs into web applications.",
        "achievements": []
      }
    ],
    "education": [
      {
        "degree": "B.Sc",
        "field": "Mathematics",
        "university": "Manonmaniam Sundarnar University",
        "year": "2020",
        "percentage": null,
        "gpa": null,
        "location": null
      },
      {
        "degree": "M.Sc",
        "field": "Mathematics",
        "university": "Manonmaniam Sundarnar University",
        "year": "2022",
        "percentage": null,
        "gpa": null,
        "location": null
      }
    ],
    "projects": [
      {
        "name": "L&T Workmen Mobilization",
        "description": "Internal Communication and Worker hiring management App",
        "techUsed": [],
        "duration": null,
        "url": null,
        "achievements": []
      },
      {
        "name": "CDMS Online University",
        "description": "E-Learning Platform",
        "techUsed": [],
        "duration": null,
        "url": null,
        "achievements": []
      },
      {
        "name": "Avtarlabs",
        "description": "E-learning Platform",
        "techUsed": [],
        "duration": null,
        "url": null,
        "achievements": []
      },
      {
        "name": "VRBIZTEC",
        "description": "Engineering Drawings - Viewing Application",
        "techUsed": [],
        "duration": null,
        "url": null,
        "achievements": []
      },
      {
        "name": "Canli",
        "description": "E-commerce Website",
        "techUsed": [],
        "duration": null,
        "url": null,
        "achievements": []
      }
    ],
    "achievements": [],
    "certifications": [
      {
        "name": "Java (Core Java)",
        "issuer": "Fita Academy, Chennai",
        "date": null,
        "expiryDate": null,
        "credentialId": null,
        "url": null
      }
    ],
    "skills": [
      "HTML5",
      "Laravel",
      "CSS3",
      "CodeIgniter",
      "JavaScript",
      "MySQL",
      "JQuery JS",
      "REST APIs",
      "PHP",
      "Moodle LMS"
    ],
    "interests": [],
    "languages": [],
    "salary": null,
    "availability": null,
    "remotePreference": null,
    "visaStatus": null,
    "originalData": {
      "filename": "Pushparani-resume.pdf",
      "rawText": "Mobile : 8489235259 E-Mail : pushparanis0905@gmail.com Github : github.com/Pushparani S LinkedIn : linkedin.com/in/pushparani-s-1437b1243 Pushparani S Web Developer SUMMARY A motivated individual with in-depth knowledge of languages and development tools, seeking a position in a growth-oriented company where I can use my skills to the advantage of the company while having the scope to develop my own skills. TECHNICAL SKILLS ◆ HTML5 ◆ Laravel ◆ CSS3 ◆ CodeIgniter ◆ JavaScript ◆ MySQL ◆ JQuery JS ◆ REST APIs ◆ PHP ◆ Moodle LMS WORK EXPERIENCE COMPANY: X-MEDIA SOLUTIONS ROLE: WEB DEVELOPER EXPERIENCE : 1 YEAR (September 2022 - PRESENT) PROJECTS: ◆ L&T Workmen Mobilization (web & mobile) - Internal Communication and Worker hiring management App ◆ CDMS Online University (web) - E-Learning Platform ◆ Avtarlabs (web) - E-learning Platform ◆ VRBIZTEC (web) - Engineering Drawings - Viewing Application ◆ Canli (website) - E-commerce Website ROLES & RESPONSIBILITIES : ◆ Design and implement database schemas for web applications. This includes creating tables, columns, and relationships, and ensuring that the schema meets the needs of the application. ◆ Integrate payment processing into web applications. This includes working with payment processors, configuring the integration, and testing the integration. ◆ Design and develop REST APIs that meet the needs of clients and users. This includes defining the API's endpoints, parameters, and responses. ◆ Integrate third-party APIs into web applications. This includes understanding the third-party API's Conducted Functional, Regression, Integration and System testing to identify the software defects. EDUCATIONAL QUALIFICATIONS BACHELOR DEGREE : B.Sc(Mathematics) - Manonmaniam Sundarnar University(2017-2020). MASTER DEGREE : M.Sc(Mathematics) - Manonmaniam Sundarnar University (2020-2022). COURSES Java (Core Java) : Fita Academy, Chennai."
    },
    "source": "resume",
    "confidence": 98,
    "processingTime": 0
  }
}