{
  "filename": "ResumeKorunamoyeeHousing.pdf",
  "timestamp": "2025-09-09T05:00:37.710Z",
  "processingTime": 15545,
  "confidence": 78,
  "rawText": "\n\n Sucheta Goswami \n                                            Email: sucheta.himu@gmail.com \n                                                                                Mobile: 9382278865   \n                                                   https://www.linkedin.com/in/sucheta-goswami-b45a90264/ \nEDUCATION    \n⚫ University College of Science and Technology ,University of Calcutta                                   Kolkata, WB, India \n  Masters of Computer Application (MCA), CGPA: 8.24                                                              Nov 2021 - Jul 2023 \n \n⚫ Asansol Girls' College, Kazi Nazrul University                                                                         Asansol, WB, India   \n              Bachelor of Science (B.Sc Hons), Computer Science, CGPA: 8.08                                           July 2018 - Sep 2021                                                   \nSKILLSET  \n⚫ Programming Language : Python, SQL, Java, HTML,CSS, Javascript. \n⚫ Frameworks : PHP Laravel, bootstrap. \n⚫ Libraries : Sklearn, Pandas, Numpy, Matplotlib \n⚫ Tools : Power BI, VsCode, Google Colab, Pycharm, Excel, Github \n⚫ Experience : Machine Learning, Clustering, Regression, Classification, Data Modeling, Data Visualization \nEXPERIENCE                                                                                                                                                            \n⚫ SCORDEMY - Technical Developer                                                                                           Aug 2023 – Present  \nRole – Working on  PHP Laravel  in Scordemy, handling backend and UI of Scordemy Learning App.  \nPROJECTS - SCORDEMY                                                                                                                                       \n• PHP Laravel Project: Student registration and purchase course’s form creation - Database configuration and \nmigration -performing crud (create, read, update, delete) operation through eloquent ORM using routing buttons - \nestablishing relation between two tables using hasone - search function-Showing customer and purchase data \nthrough table - Signup and Login page creation – using middleware and cookies to authenticate user login. \nPROJECTS - UNIVERSITY OF CALCUTTA                                                                                                       \n⚫ DEEKSHA - Learning app for Down Syndrome Children : An app comprises of learning modules and \nbasic games(drag and drop, puzzle.etc.) as assessments with a BKT(Bayesian Knowledge Tracing) model. \nPlatform - Google Colab, Android Studio. \nFront-end - Flutter.BKT(Bayesian Knowledge Tracing)  \nModel Development - Semi-Supervised Learning, Data Labeling,Agglomerative Clustering and Linear Regression. \nPROJECTS - PERSONAL                                                                                                                                         \n⚫    Pharma Sales Data Analysis using Power BI : Medicine sales report creation, Visualizing – Total Sales(month,  \nweek days and year wise), medicine wise maximum sales, Calculating sales percentage of each medicine out of      \ntotal sales, sales report creation of medicines discretely.  \n⚫    Breast Cancer Preidiction : Breast cancer prediction by predicting weather a tumor is malignant or benign. \nFrond-end – HTML, CSS. Backend – Django. Machine Learning Algorithm – Random Forest. \nProgramming Language – Python. \nSEMINARS        ___________                                                                                                                                 \n⚫ Crowd Sourcing(Task Assignment Method) : Concept, Case Study, Crowd Assessment System Architecture, \n      Task Assignment Algorithm on SocialSitu, Result Analysis.  \n⚫ Semantic Segmentation in Deep Learning : Concept, Case Study, Segmentation Mapping, Deep Learning \n      Method, Segmentation Algorithms-FCN, U-NET, PSPNet, Dialated Convolution, Pyramid Pooling Method. .   \nCERTIFICATIONS                                                                                                                                               __ \n⚫ Google Analytics for Beginners \n⚫ Certification on IBM CSRBOX: Data Analytics Internship Plan  \nINTERESTS                                                                                                                                                                 \n⚫ Reading, Playing Violin, Coding, Travel, Exploring new things. \n \nKorunamoyee Housing,  \nED block, Saltlake  \nSector – II, Bidhannagar \nPin - 731101, West Bengal \n ",
  "extractedData": {
    "name": "Sucheta Goswami",
    "email": "sucheta.himu@gmail.com",
    "phone": "9382278865",
    "linkedinUrl": "https://www.linkedin.com/in/sucheta-goswami-b45a90264/",
    "githubUrl": null,
    "portfolioUrl": null,
    "location": "Kolkata, WB, India",
    "title": null,
    "summary": null,
    "experience": [
      {
        "jobTitle": "Technical Developer",
        "company": "SCORDEMY",
        "duration": "Aug 2023 – Present",
        "startDate": "2023-08",
        "endDate": "Present",
        "techUsed": [
          "PHP Laravel"
        ],
        "description": "Working on PHP Laravel in Scordemy, handling backend and UI of Scordemy Learning App.",
        "achievements": []
      }
    ],
    "education": [
      {
        "degree": "Masters of Computer Application",
        "field": null,
        "university": "University College of Science and Technology, University of Calcutta",
        "year": "2023",
        "percentage": null,
        "gpa": "8.24",
        "location": "Kolkata, WB, India"
      },
      {
        "degree": "Bachelor of Science (B.Sc Hons)",
        "field": "Computer Science",
        "university": "Asansol Girls' College, Kazi Nazrul University",
        "year": "2021",
        "percentage": null,
        "gpa": "8.08",
        "location": "Asansol, WB, India"
      }
    ],
    "projects": [
      {
        "name": "SCORDEMY",
        "description": "PHP Laravel Project: Student registration and purchase course’s form creation - Database configuration and migration -performing crud (create, read, update, delete) operation through eloquent ORM using routing buttons - establishing relation between two tables using hasone - search function-Showing customer and purchase data through table - Signup and Login page creation – using middleware and cookies to authenticate user login.",
        "techUsed": [
          "PHP Laravel"
        ],
        "duration": null,
        "url": null,
        "achievements": []
      },
      {
        "name": "DEEKSHAA",
        "description": "Learning app for Down Syndrome Children: An app comprises of learning modules and basic games(drag and drop, puzzle.etc.) as assessments with a BKT(Bayesian Knowledge Tracing) model.",
        "techUsed": [
          "Google Colab",
          "Android Studio",
          "Flutter",
          "BKT Model"
        ],
        "duration": null,
        "url": null,
        "achievements": []
      },
      {
        "name": "Pharma Sales Data Analysis using Power BI",
        "description": "Medicine sales report creation, Visualizing – Total Sales(month, week days and year wise), medicine wise maximum sales, Calculating sales percentage of each medicine out of total sales, sales report creation of medicines discretely.",
        "techUsed": [
          "Power BI"
        ],
        "duration": null,
        "url": null,
        "achievements": []
      },
      {
        "name": "Breast Cancer Prediction",
        "description": "Breast cancer prediction by predicting whether a tumor is malignant or benign.",
        "techUsed": [
          "HTML",
          "CSS",
          "Django",
          "Random Forest",
          "Python"
        ],
        "duration": null,
        "url": null,
        "achievements": []
      }
    ],
    "achievements": [],
    "certifications": [
      {
        "name": "Google Analytics for Beginners",
        "issuer": null,
        "date": null,
        "expiryDate": null,
        "credentialId": null,
        "url": null
      },
      {
        "name": "Certification on IBM CSRBOX: Data Analytics Internship Plan",
        "issuer": null,
        "date": null,
        "expiryDate": null,
        "credentialId": null,
        "url": null
      }
    ],
    "skills": [
      "Python",
      "SQL",
      "Java",
      "HTML",
      "CSS",
      "Javascript",
      "PHP Laravel",
      "bootstrap",
      "Sklearn",
      "Pandas",
      "Numpy",
      "Matplotlib",
      "Power BI",
      "VsCode",
      "Google Colab",
      "Pycharm",
      "Excel",
      "Github",
      "Machine Learning",
      "Clustering",
      "Regression",
      "Classification",
      "Data Modeling",
      "Data Visualization"
    ],
    "interests": [
      "Reading",
      "Playing Violin",
      "Coding",
      "Travel",
      "Exploring new things"
    ],
    "languages": [],
    "salary": null,
    "availability": null,
    "remotePreference": null,
    "visaStatus": null,
    "originalData": {
      "filename": "ResumeKorunamoyeeHousing.pdf",
      "rawText": "Sucheta Goswami Email: sucheta.himu@gmail.com Mobile: 9382278865 https://www.linkedin.com/in/sucheta-goswami-b45a90264/ EDUCATION ⚫ University College of Science and Technology ,University of Calcutta Kolkata, WB, India Masters of Computer Application (MCA), CGPA: 8.24 Nov 2021 - Jul 2023 ⚫ Asansol Girls' College, Kazi Nazrul University Asansol, WB, India Bachelor of Science (B.Sc Hons), Computer Science, CGPA: 8.08 July 2018 - Sep 2021 SKILLSET ⚫ Programming Language : Python, SQL, Java, HTML,CSS, Javascript. ⚫ Frameworks : PHP Laravel, bootstrap. ⚫ Libraries : Sklearn, Pandas, Numpy, Matplotlib ⚫ Tools : Power BI, VsCode, Google Colab, Pycharm, Excel, Github ⚫ Experience : Machine Learning, Clustering, Regression, Classification, Data Modeling, Data Visualization EXPERIENCE ⚫ SCORDEMY - Technical Developer Aug 2023 – Present Role – Working on PHP Laravel in Scordemy, handling backend and UI of Scordemy Learning App. PROJECTS - SCORDEMY • PHP Laravel Project: Student registration and purchase course’s form creation - Database configuration and migration -performing crud (create, read, update, delete) operation through eloquent ORM using routing buttons - establishing relation between two tables using hasone - search function-Showing customer and purchase data through table - Signup and Login page creation – using middleware and cookies to authenticate user login. PROJECTS - UNIVERSITY OF CALCUTTA ⚫ DEEKSHA - Learning app for Down Syndrome Children : An app comprises of learning modules and basic games(drag and drop, puzzle.etc.) as assessments with a BKT(Bayesian Knowledge Tracing) model. Platform - Google Colab, Android Studio. Front-end - Flutter.BKT(Bayesian Knowledge Tracing) Model Development - Semi-Supervised Learning, Data Labeling,Agglomerative Clustering and Linear Regression. PROJECTS - PERSONAL ⚫ Pharma Sales Data Analysis using Power BI : Medicine sales report creation, Visualizing – Total Sales(month, week days and year wise), medicine wise maximum sal"
    },
    "source": "resume",
    "confidence": 78,
    "processingTime": 0
  }
}