{
  "filename": "Surya_Resume_002.pdf",
  "timestamp": "2025-09-03T12:33:52.162Z",
  "processingTime": 7158,
  "confidence": 98,
  "rawText": "\n\nSurya Murugan \nPython Developer | Software Developer  \nCurrent City: Mumbai \nEmail: surya.murugan.2026@gmail.com | Phone: 9967137495 \nLinkedIn GitHub \nProfessional Summary \nResults-driven Software and AI Developer with expertise in Python, SQL, and Django, specializing in \nmachine learning, deep learning (FastAI, Hugging Face), and AI-driven applications. Experienced in \ndeveloping finance-focused AI tools, Chrome extensions, and trading automation. Strong problem-solving \nskills with a passion for building scalable AI solutions. Seeking opportunities to apply AI and software \ndevelopment expertise to drive innovation. \n \nProfessional Experience \nJr. Software Developer \nSapat International Pvt Ltd | April 2024 – Present \n● Develop and maintain scalable backend applications using Python and Flask. \n● Design and manage RESTful APIs to enable seamless system integration. \n● Customize and extend Odoo ERP modules to meet specific business needs. \n● Enhance OpenedX LMS by implementing tailored features for better e-learning experiences. \n● Collaborate with cross-functional teams to deliver high-performance, reliable applications. \n● Utilize Open Hands platform to build and deploy AI-powered automation solutions. \n \nEducation \nBachelor of Computer Engineering (BE) \nSaraswati College of Engineering (Mumbai University) | Graduation: 2023 \n● Graduated with 7.48 CGPA (67.81%) \nHSC (Biofocal Science : Electronics) \nArya Gurukul International Jr College, Navi Mumbai, 2018 \n● Graduated with 64%\n \nTechnical Skills \n● Programming Languages: Python \n● Frameworks: Flask, Django, FastAPI, Streamlit \n● Web Development: HTML, CSS, Javascript \n● Backend Development: REST APIs, Performance Optimization \n● AI/ML Tools: Scikit-learn, OpenAI, LangGraph, HuggingFace \n● Automation:BeautifulSoup, Agentic AI, Workflow Automation \n● ERP Systems: Odoo (Customization & Extension) \n● LMS Platforms: OpenedX (Customization & Development) \n\n● Cloud Services: AWS (S3, Lambda, DynamoDB,EC2) \n● Databases: SQL, NoSQL \n● Data Processing: Web Scraping (BeautifulSoup), HTML/XML Parsing \n● Version Control: Git \n● Soft Skills: Communication, Collaboration, Problem-Solving, Mentorship \n \nKey Projects \n● QR4Order API: Developed a QR-based ordering system API for the F&B sector. \n \n● Customized OpenedX LMS: Enhanced e-learning platforms with custom feature development. \n● Event Job Portal – Developed a dynamic job portal using Django,WebSockets, enabling real-time \ncommunication, social interactions, and recruiter-employee engagement. \n● Mental Health Companion – Built an AI-powered platform integrating ML models and web \nscraping to assess mental health and recommend nearby therapists. Optimized performance using \nRedis caching. \n \nAchievements & Certifications \n● Supervised Machine Learning: Regression and Classification - DeepLearning.AI \n● AI Agent Fundamentals - HuggingFace \n \nInterests & Personal Development \n● Deep learning with Generative AI (LLMs) \n● Exploring automation and AI productivity tools \n● Staying updated with emerging technologies through continuous learning \n ",
  "extractedData": {
    "name": "Surya Murugan",
    "email": "surya.murugan.2026@gmail.com",
    "phone": "9967137495",
    "linkedinUrl": "https://www.linkedin.com/in/surya-murugan-ragaiyan/",
    "githubUrl": "https://github.com/surya-murugan-ai",
    "portfolioUrl": null,
    "location": "Mumbai",
    "title": "Python Developer | Software Developer",
    "summary": "Results-driven Software and AI Developer with expertise in Python, SQL, and Django, specializing in machine learning, deep learning (FastAI, Hugging Face), and AI-driven applications. Experienced in developing finance-focused AI tools, Chrome extensions, and trading automation. Strong problem-solving skills with a passion for building scalable AI solutions. Seeking opportunities to apply AI and software development expertise to drive innovation.",
    "experience": [
      {
        "jobTitle": "Jr. Software Developer",
        "company": "Sapat International Pvt Ltd",
        "duration": "April 2024 - Present",
        "startDate": "2024-04",
        "endDate": "Present",
        "techUsed": [
          "Python",
          "Flask",
          "RESTful APIs",
          "Odoo",
          "OpenedX",
          "AI-powered automation"
        ],
        "description": "Develop and maintain scalable backend applications using Python and Flask. Design and manage RESTful APIs to enable seamless system integration. Customize and extend Odoo ERP modules to meet specific business needs. Enhance OpenedX LMS by implementing tailored features for better e-learning experiences. Collaborate with cross-functional teams to deliver high-performance, reliable applications. Utilize Open Hands platform to build and deploy AI-powered automation solutions.",
        "achievements": []
      }
    ],
    "education": [
      {
        "degree": "Bachelor of Computer Engineering (BE)",
        "field": "Computer Engineering",
        "university": "Saraswati College of Engineering (Mumbai University)",
        "year": "2023",
        "percentage": "67.81%",
        "gpa": "7.48",
        "location": "Mumbai"
      },
      {
        "degree": "HSC",
        "field": "Biofocal Science: Electronics",
        "university": "Arya Gurukul International Jr College",
        "year": "2018",
        "percentage": "64%",
        "gpa": null,
        "location": "Navi Mumbai"
      }
    ],
    "projects": [
      {
        "name": "QR4Order API",
        "description": "Developed a QR-based ordering system API for the F&B sector.",
        "techUsed": [],
        "duration": null,
        "url": null,
        "achievements": []
      },
      {
        "name": "Customized OpenedX LMS",
        "description": "Enhanced e-learning platforms with custom feature development.",
        "techUsed": [],
        "duration": null,
        "url": null,
        "achievements": []
      },
      {
        "name": "Event Job Portal",
        "description": "Developed a dynamic job portal using Django, WebSockets, enabling real-time communication, social interactions, and recruiter-employee engagement.",
        "techUsed": [
          "Django",
          "WebSockets"
        ],
        "duration": null,
        "url": null,
        "achievements": []
      },
      {
        "name": "Mental Health Companion",
        "description": "Built an AI-powered platform integrating ML models and web scraping to assess mental health and recommend nearby therapists. Optimized performance using Redis caching.",
        "techUsed": [
          "ML models",
          "web scraping",
          "Redis caching"
        ],
        "duration": null,
        "url": null,
        "achievements": []
      }
    ],
    "achievements": [],
    "certifications": [
      {
        "name": "Supervised Machine Learning: Regression and Classification",
        "issuer": "DeepLearning.AI",
        "date": null,
        "expiryDate": null,
        "credentialId": null,
        "url": null
      },
      {
        "name": "AI Agent Fundamentals",
        "issuer": "HuggingFace",
        "date": null,
        "expiryDate": null,
        "credentialId": null,
        "url": null
      }
    ],
    "skills": [
      "Python",
      "Flask",
      "Django",
      "FastAPI",
      "Streamlit",
      "HTML",
      "CSS",
      "Javascript",
      "REST APIs",
      "Performance Optimization",
      "Scikit-learn",
      "OpenAI",
      "LangGraph",
      "HuggingFace",
      "BeautifulSoup",
      "Agentic AI",
      "Workflow Automation",
      "Odoo",
      "OpenedX",
      "AWS",
      "SQL",
      "NoSQL",
      "Web Scraping",
      "HTML/XML Parsing",
      "Git",
      "Communication",
      "Collaboration",
      "Problem-Solving",
      "Mentorship"
    ],
    "interests": [
      "Deep learning with Generative AI (LLMs)",
      "Exploring automation and AI productivity tools",
      "Staying updated with emerging technologies through continuous learning"
    ],
    "languages": [],
    "originalData": {
      "filename": "Surya_Resume_002.pdf",
      "rawText": "Surya Murugan Python Developer | Software Developer Current City: Mumbai Email: surya.murugan.2026@gmail.com | Phone: 9967137495 LinkedIn GitHub Professional Summary Results-driven Software and AI Developer with expertise in Python, SQL, and Django, specializing in machine learning, deep learning (FastAI, Hugging Face), and AI-driven applications. Experienced in developing finance-focused AI tools, Chrome extensions, and trading automation. Strong problem-solving skills with a passion for building scalable AI solutions. Seeking opportunities to apply AI and software development expertise to drive innovation. Professional Experience Jr. Software Developer Sapat International Pvt Ltd | April 2024 – Present ● Develop and maintain scalable backend applications using Python and Flask. ● Design and manage RESTful APIs to enable seamless system integration. ● Customize and extend Odoo ERP modules to meet specific business needs. ● Enhance OpenedX LMS by implementing tailored features for better e-learning experiences. ● Collaborate with cross-functional teams to deliver high-performance, reliable applications. ● Utilize Open Hands platform to build and deploy AI-powered automation solutions. Education Bachelor of Computer Engineering (BE) Saraswati College of Engineering (Mumbai University) | Graduation: 2023 ● Graduated with 7.48 CGPA (67.81%) HSC (Biofocal Science : Electronics) Arya Gurukul International Jr College, Navi Mumbai, 2018 ● Graduated with 64% Technical Skills ● Programming Languages: Python ● Frameworks: Flask, Django, FastAPI, Streamlit ● Web Development: HTML, CSS, Javascript ● Backend Development: REST APIs, Performance Optimization ● AI/ML Tools: Scikit-learn, OpenAI, LangGraph, HuggingFace ● Automation:BeautifulSoup, Agentic AI, Workflow Automation ● ERP Systems: Odoo (Customization & Extension) ● LMS Platforms: OpenedX (Customization & Development) ● Cloud Services: AWS (S3, Lambda, DynamoDB,EC2) ● Databases: SQL, NoSQL ● Data Processing: Web Scraping "
    },
    "source": "resume",
    "confidence": 98,
    "processingTime": 0
  }
}